[{"scenario_id": "arm-2-000", "arm": 2, "requester_id": "49cf612e-1afc-0eb4-efbf-1b6eacbaaa9d", "action_type": "delegate", "resource": "res_6jvgk6g004w9", "timestamp_utc": "2026-06-25T18:44:12.969745Z", "evidence_sources": {"identity": {"signal": "DENY_SIGNAL", "metadata": {"provider": "identity_provider_1", "version": "3.7"}}, "policy": {"signal": "DENY_SIGNAL", "metadata": {"provider": "policy_provider_5", "version": "1.9", "policy_id": "pol_7244"}}, "risk": {"signal": "DENY_SIGNAL", "metadata": {"provider": "risk_provider_5", "version": "2.1", "risk_score": 0.606}}, "approval": {"signal": "DENY_SIGNAL", "metadata": {"provider": "approval_provider_4", "version": "2.9", "workflow_id": "wf_82877"}}, "registry": {"signal": "DENY_SIGNAL", "metadata": {"provider": "registry_provider_1", "version": "2.1", "registry_id": "reg_332"}}, "temporal": {"signal": "DENY_SIGNAL", "metadata": {"provider": "temporal_provider_2", "version": "3.4"}}}}, {"scenario_id": "arm-2-001", "arm": 2, "requester_id": "f4d4f267-d141-4fc4-fd59-7d2cd277f1b7", "action_type": "execute", "resource": "obj_xpyszxecoymf", "timestamp_utc": "2026-06-27T00:43:12.969793Z", "evidence_sources": {"identity": {"signal": "DENY_SIGNAL", "metadata": {"provider": "identity_provider_3", "version": "2.2"}}, "policy": {"signal": "DENY_SIGNAL", "metadata": {"provider": "policy_provider_3", "version": "3.8", "policy_id": "pol_6441"}}, "risk": {"signal": "DENY_SIGNAL", "metadata": {"provider": "risk_provider_1", "version": "2.4", "risk_score": 0.946}}, "approval": {"signal": "DENY_SIGNAL", "metadata": {"provider": "approval_provider_4", "version": "2.0", "workflow_id": "wf_68082"}}, "registry": {"signal": "DENY_SIGNAL", "metadata": {"provider": "registry_provider_2", "version": "3.1", "registry_id": "reg_889"}}, "temporal": {"signal": "DENY_SIGNAL", "metadata": {"provider": "temporal_provider_5", "version": "2.7"}}}}, {"scenario_id": "arm-2-002", "arm": 2, "requester_id": "e9bfecde-db39-dbc0-5455-2fcd832894a2", "action_type": "approve", "resource": "obj_zgmwysaoyig0", "timestamp_utc": "2026-06-22T01:09:12.969815Z", "evidence_sources": {"identity": {"signal": "DENY_SIGNAL", "metadata": {"provider": "identity_provider_2", "version": "3.0"}}, "policy": {"signal": "DENY_SIGNAL", "metadata": {"provider": "policy_provider_5", "version": "2.2", "policy_id": "pol_3742"}}, "risk": {"signal": "DENY_SIGNAL", "metadata": {"provider": "risk_provider_4", "version": "1.4", "risk_score": 0.693}}, "approval": {"signal": "DENY_SIGNAL", "metadata": {"provider": "approval_provider_4", "version": "1.0", "workflow_id": "wf_21861"}}, "registry": {"signal": "DENY_SIGNAL", "metadata": {"provider": "registry_provider_2", "version": "3.0", "registry_id": "reg_158"}}, "temporal": {"signal": "DENY_SIGNAL", "metadata": {"provider": "temporal_provider_4", "version": "3.0"}}}}, {"scenario_id": "arm-2-003", "arm": 2, "requester_id": "cb1cadc9-5ae2-adcd-4cbe-a7eced6deeb7", "action_type": "transfer", "resource": "obj_vwpyjt0yhsph", "timestamp_utc": "2026-07-11T04:44:12.969836Z", "evidence_sources": {"identity": {"signal": "DENY_SIGNAL", "metadata": {"provider": "identity_provider_3", "version": "2.0"}}, "policy": {"signal": "DENY_SIGNAL", "metadata": {"provider": "policy_provider_4", "version": "3.7", "policy_id": "pol_3496"}}, "risk": {"signal": "DENY_SIGNAL", "metadata": {"provider": "risk_provider_4", "version": "3.4", "risk_score": 0.688}}, "approval": {"signal": "DENY_SIGNAL", "metadata": {"provider": "approval_provider_4", "version": "1.5", "workflow_id": "wf_37237"}}, "registry": {"signal": "DENY_SIGNAL", "metadata": {"provider": "registry_provider_4", "version": "2.4", "registry_id": "reg_459"}}, "temporal": {"signal": "DENY_SIGNAL", "metadata": {"provider": "temporal_provider_3", "version": "2.5"}}}}, {"scenario_id": "arm-2-004", "arm": 2, "requester_id": "87076b5f-ba1a-41c6-ad77-f8dd635f5b0d", "action_type": "execute", "resource": "res_8ib2ge4xls1t", "timestamp_utc": "2026-07-05T13:45:12.969857Z", "evidence_sources": {"identity": {"signal": "DENY_SIGNAL", "metadata": {"provider": "identity_provider_1", "version": "2.5"}}, "policy": {"signal": "DENY_SIGNAL", "metadata": {"provider": "policy_provider_3", "version": "1.3", "policy_id": "pol_5005"}}, "risk": {"signal": "DENY_SIGNAL", "metadata": {"provider": "risk_provider_4", "version": "3.7", "risk_score": 0.354}}, "approval": {"signal": "DENY_SIGNAL", "metadata": {"provider": "approval_provider_2", "version": "3.5", "workflow_id": "wf_22526"}}, "registry": {"signal": "DENY_SIGNAL", "metadata": {"provider": "registry_provider_5", "version": "2.3", "registry_id": "reg_162"}}, "temporal": {"signal": "DENY_SIGNAL", "metadata": {"provider": "temporal_provider_2", "version": "1.2"}}}}, {"scenario_id": "arm-2-005", "arm": 2, "requester_id": "0ea62cf6-22ed-d5b5-ccc0-940de4f75b20", "action_type": "execute", "resource": "obj_z682hbvoz9op", "timestamp_utc": "2026-07-15T02:43:12.969877Z", "evidence_sources": {"identity": {"signal": "DENY_SIGNAL", "metadata": {"provider": "identity_provider_5", "version": "2.1"}}, "policy": {"signal": "DENY_SIGNAL", "metadata": {"provider": "policy_provider_2", "version": "3.9", "policy_id": "pol_4174"}}, "risk": {"signal": "DENY_SIGNAL", "metadata": {"provider": "risk_provider_4", "version": "3.7", "risk_score": 0.284}}, "approval": {"signal": "DENY_SIGNAL", "metadata": {"provider": "approval_provider_3", "version": "3.8", "workflow_id": "wf_26896"}}, "registry": {"signal": "DENY_SIGNAL", "metadata": {"provider": "registry_provider_4", "version": "3.3", "registry_id": "reg_988"}}, "temporal": {"signal": "DENY_SIGNAL", "metadata": {"provider": "temporal_provider_5", "version": "2.5"}}}}, {"scenario_id": "arm-2-006", "arm": 2, "requester_id": "403b2d0f-e047-330c-a2dd-d4e5fd843323", "action_type": "transfer", "resource": "res_a99102bbyt7s", "timestamp_utc": "2026-06-27T07:47:12.969897Z", "evidence_sources": {"identity": {"signal": "DENY_SIGNAL", "metadata": {"provider": "identity_provider_2", "version": "3.8"}}, "policy": {"signal": "DENY_SIGNAL", "metadata": {"provider": "policy_provider_3", "version": "1.9", "policy_id": "pol_3741"}}, "risk": {"signal": "DENY_SIGNAL", "metadata": {"provider": "risk_provider_2", "version": "2.2", "risk_score": 0.636}}, "approval": {"signal": "DENY_SIGNAL", "metadata": {"provider": "approval_provider_3", "version": "3.3", "workflow_id": "wf_50769"}}, "registry": {"signal": "DENY_SIGNAL", "metadata": {"provider": "registry_provider_4", "version": "2.6", "registry_id": "reg_767"}}, "temporal": {"signal": "DENY_SIGNAL", "metadata": {"provider": "temporal_provider_5", "version": "3.3"}}}}, {"scenario_id": "arm-2-007", "arm": 2, "requester_id": "fed8867f-de0c-1da9-c40e-fb4b5c8eaeef", "action_type": "revoke", "resource": "asset_5oyca7er0ffb", "timestamp_utc": "2026-06-19T06:36:12.969916Z", "evidence_sources": {"identity": {"signal": "DENY_SIGNAL", "metadata": {"provider": "identity_provider_1", "version": "1.9"}}, "policy": {"signal": "DENY_SIGNAL", "metadata": {"provider": "policy_provider_3", "version": "2.6", "policy_id": "pol_1518"}}, "risk": {"signal": "DENY_SIGNAL", "metadata": {"provider": "risk_provider_3", "version": "3.1", "risk_score": 0.748}}, "approval": {"signal": "DENY_SIGNAL", "metadata": {"provider": "approval_provider_3", "version": "3.9", "workflow_id": "wf_73759"}}, "registry": {"signal": "DENY_SIGNAL", "metadata": {"provider": "registry_provider_3", "version": "1.8", "registry_id": "reg_346"}}, "temporal": {"signal": "DENY_SIGNAL", "metadata": {"provider": "temporal_provider_2", "version": "3.5"}}}}, {"scenario_id": "arm-2-008", "arm": 2, "requester_id": "53ee29a3-ada9-8b99-c068-56accd92efc2", "action_type": "transfer", "resource": "res_489xbl6z07lu", "timestamp_utc": "2026-07-10T22:37:12.969937Z", "evidence_sources": {"identity": {"signal": "DENY_SIGNAL", "metadata": {"provider": "identity_provider_5", "version": "1.7"}}, "policy": {"signal": "DENY_SIGNAL", "metadata": {"provider": "policy_provider_3", "version": "1.4", "policy_id": "pol_8625"}}, "risk": {"signal": "DENY_SIGNAL", "metadata": {"provider": "risk_provider_2", "version": "2.0", "risk_score": 0.072}}, "approval": {"signal": "DENY_SIGNAL", "metadata": {"provider": "approval_provider_1", "version": "3.4", "workflow_id": "wf_57581"}}, "registry": {"signal": "DENY_SIGNAL", "metadata": {"provider": "registry_provider_2", "version": "2.7", "registry_id": "reg_736"}}, "temporal": {"signal": "DENY_SIGNAL", "metadata": {"provider": "temporal_provider_1", "version": "2.5"}}}}, {"scenario_id": "arm-2-009", "arm": 2, "requester_id": "dcedf3d8-9652-bbab-28a3-3fd1ba3f92d6", "action_type": "revoke", "resource": "obj_sb571fj5jub2", "timestamp_utc": "2026-07-11T05:19:12.969957Z", "evidence_sources": {"identity": {"signal": "DENY_SIGNAL", "metadata": {"provider": "identity_provider_4", "version": "2.4"}}, "policy": {"signal": "DENY_SIGNAL", "metadata": {"provider": "policy_provider_4", "version": "2.2", "policy_id": "pol_9836"}}, "risk": {"signal": "DENY_SIGNAL", "metadata": {"provider": "risk_provider_3", "version": "2.3", "risk_score": 0.747}}, "approval": {"signal": "DENY_SIGNAL", "metadata": {"provider": "approval_provider_4", "version": "2.8", "workflow_id": "wf_63076"}}, "registry": {"signal": "DENY_SIGNAL", "metadata": {"provider": "registry_provider_3", "version": "3.8", "registry_id": "reg_418"}}, "temporal": {"signal": "DENY_SIGNAL", "metadata": {"provider": "temporal_provider_5", "version": "1.2"}}}}, {"scenario_id": "arm-2-010", "arm": 2, "requester_id": "3bdcefa4-f2d1-41fd-ac47-2646cabfaeeb", "action_type": "execute", "resource": "res_5i80dc6c8tf2", "timestamp_utc": "2026-06-27T15:59:12.969977Z", "evidence_sources": {"identity": {"signal": "DENY_SIGNAL", "metadata": {"provider": "identity_provider_4", "version": "2.4"}}, "policy": {"signal": "DENY_SIGNAL", "metadata": {"provider": "policy_provider_4", "version": "1.5", "policy_id": "pol_9049"}}, "risk": {"signal": "DENY_SIGNAL", "metadata": {"provider": "risk_provider_2", "version": "1.9", "risk_score": 0.674}}, "approval": {"signal": "DENY_SIGNAL", "metadata": {"provider": "approval_provider_2", "version": "2.9", "workflow_id": "wf_83426"}}, "registry": {"signal": "DENY_SIGNAL", "metadata": {"provider": "registry_provider_1", "version": "1.9", "registry_id": "reg_157"}}, "temporal": {"signal": "DENY_SIGNAL", "metadata": {"provider": "temporal_provider_2", "version": "3.6"}}}}, {"scenario_id": "arm-2-011", "arm": 2, "requester_id": "6dd6dc1c-b504-d2ab-89f7-22cfe6f4bad8", "action_type": "execute", "resource": "asset_gm8k0im4vh9s", "timestamp_utc": "2026-07-11T22:52:12.969996Z", "evidence_sources": {"identity": {"signal": "DENY_SIGNAL", "metadata": {"provider": "identity_provider_5", "version": "2.1"}}, "policy": {"signal": "DENY_SIGNAL", "metadata": {"provider": "policy_provider_2", "version": "3.4", "policy_id": "pol_9898"}}, "risk": {"signal": "DENY_SIGNAL", "metadata": {"provider": "risk_provider_4", "version": "1.2", "risk_score": 0.916}}, "approval": {"signal": "DENY_SIGNAL", "metadata": {"provider": "approval_provider_4", "version": "2.2", "workflow_id": "wf_51789"}}, "registry": {"signal": "DENY_SIGNAL", "metadata": {"provider": "registry_provider_2", "version": "2.4", "registry_id": "reg_337"}}, "temporal": {"signal": "DENY_SIGNAL", "metadata": {"provider": "temporal_provider_1", "version": "2.7"}}}}, {"scenario_id": "arm-2-012", "arm": 2, "requester_id": "a78ec0f3-44b9-97b0-f60c-1bc5401cfa35", "action_type": "delegate", "resource": "res_csuaekx1ce7g", "timestamp_utc": "2026-07-08T20:48:12.970016Z", "evidence_sources": {"identity": {"signal": "DENY_SIGNAL", "metadata": {"provider": "identity_provider_3", "version": "1.6"}}, "policy": {"signal": "DENY_SIGNAL", "metadata": {"provider": "policy_provider_5", "version": "2.4", "policy_id": "pol_3465"}}, "risk": {"signal": "DENY_SIGNAL", "metadata": {"provider": "risk_provider_4", "version": "1.3", "risk_score": 0.968}}, "approval": {"signal": "DENY_SIGNAL", "metadata": {"provider": "approval_provider_1", "version": "1.4", "workflow_id": "wf_89538"}}, "registry": {"signal": "DENY_SIGNAL", "metadata": {"provider": "registry_provider_4", "version": "1.3", "registry_id": "reg_311"}}, "temporal": {"signal": "DENY_SIGNAL", "metadata": {"provider": "temporal_provider_1", "version": "1.1"}}}}, {"scenario_id": "arm-2-013", "arm": 2, "requester_id": "8cc4da00-2986-0f3f-edeb-8cfbe6f51003", "action_type": "execute", "resource": "asset_m5tz0j8811zj", "timestamp_utc": "2026-07-14T08:12:12.970036Z", "evidence_sources": {"identity": {"signal": "DENY_SIGNAL", "metadata": {"provider": "identity_provider_4", "version": "1.7"}}, "policy": {"signal": "DENY_SIGNAL", "metadata": {"provider": "policy_provider_2", "version": "1.9", "policy_id": "pol_5017"}}, "risk": {"signal": "DENY_SIGNAL", "metadata": {"provider": "risk_provider_5", "version": "3.3", "risk_score": 0.829}}, "approval": {"signal": "DENY_SIGNAL", "metadata": {"provider": "approval_provider_2", "version": "1.6", "workflow_id": "wf_75347"}}, "registry": {"signal": "DENY_SIGNAL", "metadata": {"provider": "registry_provider_3", "version": "1.4", "registry_id": "reg_968"}}, "temporal": {"signal": "DENY_SIGNAL", "metadata": {"provider": "temporal_provider_2", "version": "2.4"}}}}, {"scenario_id": "arm-2-014", "arm": 2, "requester_id": "29f044ef-dcc1-c9a0-c6c1-f5ba94b85985", "action_type": "revoke", "resource": "asset_jr3xujccdler", "timestamp_utc": "2026-06-27T13:25:12.970056Z", "evidence_sources": {"identity": {"signal": "DENY_SIGNAL", "metadata": {"provider": "identity_provider_1", "version": "1.0"}}, "policy": {"signal": "DENY_SIGNAL", "metadata": {"provider": "policy_provider_4", "version": "3.6", "policy_id": "pol_6687"}}, "risk": {"signal": "DENY_SIGNAL", "metadata": {"provider": "risk_provider_3", "version": "1.3", "risk_score": 0.095}}, "approval": {"signal": "DENY_SIGNAL", "metadata": {"provider": "approval_provider_3", "version": "1.1", "workflow_id": "wf_73291"}}, "registry": {"signal": "DENY_SIGNAL", "metadata": {"provider": "registry_provider_3", "version": "2.2", "registry_id": "reg_760"}}, "temporal": {"signal": "DENY_SIGNAL", "metadata": {"provider": "temporal_provider_3", "version": "3.9"}}}}, {"scenario_id": "arm-2-015", "arm": 2, "requester_id": "ef6f7fe2-ad87-f04a-7084-c6e7bbbc8aee", "action_type": "approve", "resource": "item_o96voxjwfuez", "timestamp_utc": "2026-06-18T10:06:12.970076Z", "evidence_sources": {"identity": {"signal": "DENY_SIGNAL", "metadata": {"provider": "identity_provider_5", "version": "2.3"}}, "policy": {"signal": "DENY_SIGNAL", "metadata": {"provider": "policy_provider_3", "version": "2.9", "policy_id": "pol_1887"}}, "risk": {"signal": "DENY_SIGNAL", "metadata": {"provider": "risk_provider_3", "version": "2.2", "risk_score": 0.277}}, "approval": {"signal": "DENY_SIGNAL", "metadata": {"provider": "approval_provider_1", "version": "1.7", "workflow_id": "wf_55028"}}, "registry": {"signal": "DENY_SIGNAL", "metadata": {"provider": "registry_provider_4", "version": "3.9", "registry_id": "reg_834"}}, "temporal": {"signal": "DENY_SIGNAL", "metadata": {"provider": "temporal_provider_4", "version": "3.0"}}}}, {"scenario_id": "arm-2-016", "arm": 2, "requester_id": "abfc360f-c9ca-825a-0b15-abb788cb30ee", "action_type": "transfer", "resource": "item_qvgqdvi877oa", "timestamp_utc": "2026-06-27T08:15:12.970095Z", "evidence_sources": {"identity": {"signal": "DENY_SIGNAL", "metadata": {"provider": "identity_provider_5", "version": "2.9"}}, "policy": {"signal": "DENY_SIGNAL", "metadata": {"provider": "policy_provider_4", "version": "1.9", "policy_id": "pol_4574"}}, "risk": {"signal": "DENY_SIGNAL", "metadata": {"provider": "risk_provider_5", "version": "3.3", "risk_score": 0.35}}, "approval": {"signal": "DENY_SIGNAL", "metadata": {"provider": "approval_provider_5", "version": "2.0", "workflow_id": "wf_17778"}}, "registry": {"signal": "DENY_SIGNAL", "metadata": {"provider": "registry_provider_1", "version": "3.5", "registry_id": "reg_102"}}, "temporal": {"signal": "DENY_SIGNAL", "metadata": {"provider": "temporal_provider_5", "version": "1.9"}}}}, {"scenario_id": "arm-2-017", "arm": 2, "requester_id": "fff324cd-faeb-af04-b537-4aebfd3fac48", "action_type": "revoke", "resource": "asset_5uq319m365wv", "timestamp_utc": "2026-06-29T19:25:12.970114Z", "evidence_sources": {"identity": {"signal": "DENY_SIGNAL", "metadata": {"provider": "identity_provider_1", "version": "2.5"}}, "policy": {"signal": "DENY_SIGNAL", "metadata": {"provider": "policy_provider_2", "version": "3.5", "policy_id": "pol_5509"}}, "risk": {"signal": "DENY_SIGNAL", "metadata": {"provider": "risk_provider_3", "version": "2.0", "risk_score": 0.665}}, "approval": {"signal": "DENY_SIGNAL", "metadata": {"provider": "approval_provider_1", "version": "2.4", "workflow_id": "wf_68319"}}, "registry": {"signal": "DENY_SIGNAL", "metadata": {"provider": "registry_provider_1", "version": "3.1", "registry_id": "reg_145"}}, "temporal": {"signal": "DENY_SIGNAL", "metadata": {"provider": "temporal_provider_2", "version": "3.7"}}}}, {"scenario_id": "arm-2-018", "arm": 2, "requester_id": "b6f2b95d-eaca-78b9-d5ad-04d1cbdc1c8d", "action_type": "delegate", "resource": "res_z853hb803xto", "timestamp_utc": "2026-06-28T11:22:12.970135Z", "evidence_sources": {"identity": {"signal": "DENY_SIGNAL", "metadata": {"provider": "identity_provider_1", "version": "3.0"}}, "policy": {"signal": "DENY_SIGNAL", "metadata": {"provider": "policy_provider_3", "version": "3.2", "policy_id": "pol_8330"}}, "risk": {"signal": "DENY_SIGNAL", "metadata": {"provider": "risk_provider_5", "version": "3.5", "risk_score": 0.718}}, "approval": {"signal": "DENY_SIGNAL", "metadata": {"provider": "approval_provider_1", "version": "2.4", "workflow_id": "wf_86258"}}, "registry": {"signal": "DENY_SIGNAL", "metadata": {"provider": "registry_provider_3", "version": "1.1", "registry_id": "reg_525"}}, "temporal": {"signal": "DENY_SIGNAL", "metadata": {"provider": "temporal_provider_4", "version": "1.2"}}}}, {"scenario_id": "arm-2-019", "arm": 2, "requester_id": "9fafc3e7-4c56-8eab-bdcc-9d61a8dd23ca", "action_type": "execute", "resource": "obj_lmii0i3q6byh", "timestamp_utc": "2026-06-25T11:38:12.970260Z", "evidence_sources": {"identity": {"signal": "DENY_SIGNAL", "metadata": {"provider": "identity_provider_5", "version": "1.2"}}, "policy": {"signal": "DENY_SIGNAL", "metadata": {"provider": "policy_provider_4", "version": "3.7", "policy_id": "pol_8429"}}, "risk": {"signal": "DENY_SIGNAL", "metadata": {"provider": "risk_provider_4", "version": "1.2", "risk_score": 0.856}}, "approval": {"signal": "DENY_SIGNAL", "metadata": {"provider": "approval_provider_2", "version": "3.3", "workflow_id": "wf_16583"}}, "registry": {"signal": "DENY_SIGNAL", "metadata": {"provider": "registry_provider_1", "version": "3.3", "registry_id": "reg_396"}}, "temporal": {"signal": "DENY_SIGNAL", "metadata": {"provider": "temporal_provider_4", "version": "3.5"}}}}, {"scenario_id": "arm-2-020", "arm": 2, "requester_id": "fbb5998f-372e-1b9c-2bab-00c7ed98fe39", "action_type": "approve", "resource": "asset_du7zwrvbd7p4", "timestamp_utc": "2026-07-13T05:11:12.970290Z", "evidence_sources": {"identity": {"signal": "DENY_SIGNAL", "metadata": {"provider": "identity_provider_5", "version": "3.0"}}, "policy": {"signal": "DENY_SIGNAL", "metadata": {"provider": "policy_provider_1", "version": "2.2", "policy_id": "pol_2593"}}, "risk": {"signal": "DENY_SIGNAL", "metadata": {"provider": "risk_provider_2", "version": "1.3", "risk_score": 0.43}}, "approval": {"signal": "DENY_SIGNAL", "metadata": {"provider": "approval_provider_2", "version": "2.2", "workflow_id": "wf_34190"}}, "registry": {"signal": "DENY_SIGNAL", "metadata": {"provider": "registry_provider_2", "version": "1.7", "registry_id": "reg_813"}}, "temporal": {"signal": "DENY_SIGNAL", "metadata": {"provider": "temporal_provider_4", "version": "2.3"}}}}, {"scenario_id": "arm-2-021", "arm": 2, "requester_id": "0f4bdedd-1b7f-fdd2-aecc-1a257aee3d0d", "action_type": "revoke", "resource": "asset_na4otgv9yqke", "timestamp_utc": "2026-07-17T18:00:12.970317Z", "evidence_sources": {"identity": {"signal": "DENY_SIGNAL", "metadata": {"provider": "identity_provider_3", "version": "3.4"}}, "policy": {"signal": "DENY_SIGNAL", "metadata": {"provider": "policy_provider_1", "version": "2.0", "policy_id": "pol_2362"}}, "risk": {"signal": "DENY_SIGNAL", "metadata": {"provider": "risk_provider_5", "version": "3.0", "risk_score": 0.692}}, "approval": {"signal": "DENY_SIGNAL", "metadata": {"provider": "approval_provider_5", "version": "3.2", "workflow_id": "wf_37811"}}, "registry": {"signal": "DENY_SIGNAL", "metadata": {"provider": "registry_provider_3", "version": "3.5", "registry_id": "reg_236"}}, "temporal": {"signal": "DENY_SIGNAL", "metadata": {"provider": "temporal_provider_3", "version": "2.6"}}}}, {"scenario_id": "arm-2-022", "arm": 2, "requester_id": "0ac0fc85-13df-2a3e-bd59-8a7d966aad8d", "action_type": "delegate", "resource": "asset_gg03xq6wkesh", "timestamp_utc": "2026-06-23T17:19:12.970348Z", "evidence_sources": {"identity": {"signal": "DENY_SIGNAL", "metadata": {"provider": "identity_provider_4", "version": "1.3"}}, "policy": {"signal": "DENY_SIGNAL", "metadata": {"provider": "policy_provider_4", "version": "3.6", "policy_id": "pol_3717"}}, "risk": {"signal": "DENY_SIGNAL", "metadata": {"provider": "risk_provider_5", "version": "2.2", "risk_score": 0.905}}, "approval": {"signal": "DENY_SIGNAL", "metadata": {"provider": "approval_provider_5", "version": "2.8", "workflow_id": "wf_43717"}}, "registry": {"signal": "DENY_SIGNAL", "metadata": {"provider": "registry_provider_3", "version": "1.8", "registry_id": "reg_652"}}, "temporal": {"signal": "DENY_SIGNAL", "metadata": {"provider": "temporal_provider_5", "version": "2.4"}}}}, {"scenario_id": "arm-2-023", "arm": 2, "requester_id": "981ed3fb-faa8-fef1-d2cf-efed8ffceeaf", "action_type": "approve", "resource": "asset_l8h2r96dt4cj", "timestamp_utc": "2026-07-16T06:45:12.970375Z", "evidence_sources": {"identity": {"signal": "DENY_SIGNAL", "metadata": {"provider": "identity_provider_3", "version": "1.2"}}, "policy": {"signal": "DENY_SIGNAL", "metadata": {"provider": "policy_provider_3", "version": "2.6", "policy_id": "pol_4862"}}, "risk": {"signal": "DENY_SIGNAL", "metadata": {"provider": "risk_provider_1", "version": "2.5", "risk_score": 0.707}}, "approval": {"signal": "DENY_SIGNAL", "metadata": {"provider": "approval_provider_5", "version": "1.1", "workflow_id": "wf_80677"}}, "registry": {"signal": "DENY_SIGNAL", "metadata": {"provider": "registry_provider_3", "version": "1.2", "registry_id": "reg_629"}}, "temporal": {"signal": "DENY_SIGNAL", "metadata": {"provider": "temporal_provider_3", "version": "3.7"}}}}, {"scenario_id": "arm-2-024", "arm": 2, "requester_id": "c3df50ba-c654-72a8-08c3-11a438d8aff4", "action_type": "revoke", "resource": "item_7wygn9ohu2j8", "timestamp_utc": "2026-07-13T03:59:12.970403Z", "evidence_sources": {"identity": {"signal": "DENY_SIGNAL", "metadata": {"provider": "identity_provider_5", "version": "1.5"}}, "policy": {"signal": "DENY_SIGNAL", "metadata": {"provider": "policy_provider_2", "version": "3.1", "policy_id": "pol_8557"}}, "risk": {"signal": "DENY_SIGNAL", "metadata": {"provider": "risk_provider_1", "version": "3.1", "risk_score": 0.529}}, "approval": {"signal": "DENY_SIGNAL", "metadata": {"provider": "approval_provider_4", "version": "1.1", "workflow_id": "wf_21216"}}, "registry": {"signal": "DENY_SIGNAL", "metadata": {"provider": "registry_provider_5", "version": "2.8", "registry_id": "reg_686"}}, "temporal": {"signal": "DENY_SIGNAL", "metadata": {"provider": "temporal_provider_1", "version": "2.8"}}}}, {"scenario_id": "arm-2-025", "arm": 2, "requester_id": "09178d0d-5c0e-50be-ec8b-7b6b862f1bf2", "action_type": "approve", "resource": "asset_4lrlwyxdo36b", "timestamp_utc": "2026-07-09T21:46:12.970437Z", "evidence_sources": {"identity": {"signal": "DENY_SIGNAL", "metadata": {"provider": "identity_provider_3", "version": "2.9"}}, "policy": {"signal": "DENY_SIGNAL", "metadata": {"provider": "policy_provider_4", "version": "1.4", "policy_id": "pol_1976"}}, "risk": {"signal": "DENY_SIGNAL", "metadata": {"provider": "risk_provider_3", "version": "1.9", "risk_score": 0.562}}, "approval": {"signal": "DENY_SIGNAL", "metadata": {"provider": "approval_provider_3", "version": "3.7", "workflow_id": "wf_65656"}}, "registry": {"signal": "DENY_SIGNAL", "metadata": {"provider": "registry_provider_2", "version": "2.2", "registry_id": "reg_855"}}, "temporal": {"signal": "DENY_SIGNAL", "metadata": {"provider": "temporal_provider_2", "version": "3.0"}}}}, {"scenario_id": "arm-2-026", "arm": 2, "requester_id": "baeeeba6-ce3d-8bcf-1610-ca8c5afc2ebd", "action_type": "transfer", "resource": "asset_cynfkbvaetj3", "timestamp_utc": "2026-07-01T10:50:12.970466Z", "evidence_sources": {"identity": {"signal": "DENY_SIGNAL", "metadata": {"provider": "identity_provider_3", "version": "3.4"}}, "policy": {"signal": "DENY_SIGNAL", "metadata": {"provider": "policy_provider_3", "version": "2.8", "policy_id": "pol_8334"}}, "risk": {"signal": "DENY_SIGNAL", "metadata": {"provider": "risk_provider_1", "version": "2.0", "risk_score": 0.25}}, "approval": {"signal": "DENY_SIGNAL", "metadata": {"provider": "approval_provider_4", "version": "1.8", "workflow_id": "wf_85765"}}, "registry": {"signal": "DENY_SIGNAL", "metadata": {"provider": "registry_provider_3", "version": "1.0", "registry_id": "reg_137"}}, "temporal": {"signal": "DENY_SIGNAL", "metadata": {"provider": "temporal_provider_3", "version": "1.5"}}}}, {"scenario_id": "arm-2-027", "arm": 2, "requester_id": "dc7bbbfd-4cbf-0f9b-d6a3-c53c5f6baa9a", "action_type": "approve", "resource": "item_21tkh67kg34q", "timestamp_utc": "2026-07-12T21:16:12.970496Z", "evidence_sources": {"identity": {"signal": "DENY_SIGNAL", "metadata": {"provider": "identity_provider_3", "version": "3.0"}}, "policy": {"signal": "DENY_SIGNAL", "metadata": {"provider": "policy_provider_1", "version": "2.7", "policy_id": "pol_8735"}}, "risk": {"signal": "DENY_SIGNAL", "metadata": {"provider": "risk_provider_4", "version": "3.6", "risk_score": 0.048}}, "approval": {"signal": "DENY_SIGNAL", "metadata": {"provider": "approval_provider_3", "version": "1.8", "workflow_id": "wf_56200"}}, "registry": {"signal": "DENY_SIGNAL", "metadata": {"provider": "registry_provider_5", "version": "1.0", "registry_id": "reg_744"}}, "temporal": {"signal": "DENY_SIGNAL", "metadata": {"provider": "temporal_provider_2", "version": "1.2"}}}}, {"scenario_id": "arm-2-028", "arm": 2, "requester_id": "8729fab4-106e-b4fd-abde-1ffacdf484af", "action_type": "transfer", "resource": "obj_15crzo6d640u", "timestamp_utc": "2026-07-04T07:18:12.970525Z", "evidence_sources": {"identity": {"signal": "DENY_SIGNAL", "metadata": {"provider": "identity_provider_1", "version": "3.0"}}, "policy": {"signal": "DENY_SIGNAL", "metadata": {"provider": "policy_provider_4", "version": "2.0", "policy_id": "pol_1895"}}, "risk": {"signal": "DENY_SIGNAL", "metadata": {"provider": "risk_provider_5", "version": "2.7", "risk_score": 0.969}}, "approval": {"signal": "DENY_SIGNAL", "metadata": {"provider": "approval_provider_4", "version": "2.9", "workflow_id": "wf_18984"}}, "registry": {"signal": "DENY_SIGNAL", "metadata": {"provider": "registry_provider_3", "version": "3.7", "registry_id": "reg_747"}}, "temporal": {"signal": "DENY_SIGNAL", "metadata": {"provider": "temporal_provider_4", "version": "2.9"}}}}, {"scenario_id": "arm-2-029", "arm": 2, "requester_id": "ecdc6dcb-62fa-21ea-dba0-3f9dadcbb2b4", "action_type": "execute", "resource": "item_6ghs5963hpy4", "timestamp_utc": "2026-07-11T04:15:12.970552Z", "evidence_sources": {"identity": {"signal": "DENY_SIGNAL", "metadata": {"provider": "identity_provider_3", "version": "3.1"}}, "policy": {"signal": "DENY_SIGNAL", "metadata": {"provider": "policy_provider_4", "version": "3.7", "policy_id": "pol_7817"}}, "risk": {"signal": "DENY_SIGNAL", "metadata": {"provider": "risk_provider_2", "version": "2.7", "risk_score": 0.769}}, "approval": {"signal": "DENY_SIGNAL", "metadata": {"provider": "approval_provider_5", "version": "1.0", "workflow_id": "wf_99169"}}, "registry": {"signal": "DENY_SIGNAL", "metadata": {"provider": "registry_provider_2", "version": "1.3", "registry_id": "reg_645"}}, "temporal": {"signal": "DENY_SIGNAL", "metadata": {"provider": "temporal_provider_5", "version": "3.3"}}}}, {"scenario_id": "arm-2-030", "arm": 2, "requester_id": "982fbfa4-4c51-8dca-1aea-b3fcbf7da923", "action_type": "approve", "resource": "item_klysmd9pspe2", "timestamp_utc": "2026-06-17T19:55:12.970585Z", "evidence_sources": {"identity": {"signal": "DENY_SIGNAL", "metadata": {"provider": "identity_provider_4", "version": "2.4"}}, "policy": {"signal": "DENY_SIGNAL", "metadata": {"provider": "policy_provider_4", "version": "3.3", "policy_id": "pol_9330"}}, "risk": {"signal": "DENY_SIGNAL", "metadata": {"provider": "risk_provider_2", "version": "1.4", "risk_score": 0.732}}, "approval": {"signal": "DENY_SIGNAL", "metadata": {"provider": "approval_provider_2", "version": "1.6", "workflow_id": "wf_55690"}}, "registry": {"signal": "DENY_SIGNAL", "metadata": {"provider": "registry_provider_5", "version": "2.6", "registry_id": "reg_217"}}, "temporal": {"signal": "DENY_SIGNAL", "metadata": {"provider": "temporal_provider_5", "version": "1.0"}}}}, {"scenario_id": "arm-2-031", "arm": 2, "requester_id": "ca505aec-bbed-6fdd-ad9f-c511ea07f7ea", "action_type": "delegate", "resource": "asset_w5zmxy3l6f8v", "timestamp_utc": "2026-06-26T19:31:12.970613Z", "evidence_sources": {"identity": {"signal": "DENY_SIGNAL", "metadata": {"provider": "identity_provider_5", "version": "1.6"}}, "policy": {"signal": "DENY_SIGNAL", "metadata": {"provider": "policy_provider_4", "version": "3.7", "policy_id": "pol_7854"}}, "risk": {"signal": "DENY_SIGNAL", "metadata": {"provider": "risk_provider_1", "version": "2.9", "risk_score": 0.996}}, "approval": {"signal": "DENY_SIGNAL", "metadata": {"provider": "approval_provider_2", "version": "1.5", "workflow_id": "wf_77940"}}, "registry": {"signal": "DENY_SIGNAL", "metadata": {"provider": "registry_provider_4", "version": "2.8", "registry_id": "reg_925"}}, "temporal": {"signal": "DENY_SIGNAL", "metadata": {"provider": "temporal_provider_5", "version": "3.6"}}}}, {"scenario_id": "arm-2-032", "arm": 2, "requester_id": "ec1daae3-48df-2bb0-b81a-cc0fd140272e", "action_type": "delegate", "resource": "item_eunitl9rubwh", "timestamp_utc": "2026-06-18T05:59:12.970643Z", "evidence_sources": {"identity": {"signal": "DENY_SIGNAL", "metadata": {"provider": "identity_provider_3", "version": "3.1"}}, "policy": {"signal": "DENY_SIGNAL", "metadata": {"provider": "policy_provider_5", "version": "1.0", "policy_id": "pol_6911"}}, "risk": {"signal": "DENY_SIGNAL", "metadata": {"provider": "risk_provider_1", "version": "2.8", "risk_score": 0.658}}, "approval": {"signal": "DENY_SIGNAL", "metadata": {"provider": "approval_provider_5", "version": "3.8", "workflow_id": "wf_53930"}}, "registry": {"signal": "DENY_SIGNAL", "metadata": {"provider": "registry_provider_5", "version": "3.8", "registry_id": "reg_754"}}, "temporal": {"signal": "DENY_SIGNAL", "metadata": {"provider": "temporal_provider_2", "version": "3.9"}}}}, {"scenario_id": "arm-2-033", "arm": 2, "requester_id": "abedc899-e688-50c4-febc-bdd3ac2cf9af", "action_type": "revoke", "resource": "item_dj8iwmszejjb", "timestamp_utc": "2026-06-27T22:37:12.970671Z", "evidence_sources": {"identity": {"signal": "DENY_SIGNAL", "metadata": {"provider": "identity_provider_5", "version": "3.9"}}, "policy": {"signal": "DENY_SIGNAL", "metadata": {"provider": "policy_provider_1", "version": "1.1", "policy_id": "pol_8230"}}, "risk": {"signal": "DENY_SIGNAL", "metadata": {"provider": "risk_provider_2", "version": "2.0", "risk_score": 0.217}}, "approval": {"signal": "DENY_SIGNAL", "metadata": {"provider": "approval_provider_3", "version": "2.1", "workflow_id": "wf_33800"}}, "registry": {"signal": "DENY_SIGNAL", "metadata": {"provider": "registry_provider_2", "version": "2.5", "registry_id": "reg_108"}}, "temporal": {"signal": "DENY_SIGNAL", "metadata": {"provider": "temporal_provider_4", "version": "2.6"}}}}, {"scenario_id": "arm-2-034", "arm": 2, "requester_id": "edcd8ea5-b18c-75ca-4361-fca93beb7ac5", "action_type": "execute", "resource": "obj_ofnrh3sr5qfe", "timestamp_utc": "2026-07-13T16:13:12.970702Z", "evidence_sources": {"identity": {"signal": "DENY_SIGNAL", "metadata": {"provider": "identity_provider_4", "version": "3.5"}}, "policy": {"signal": "DENY_SIGNAL", "metadata": {"provider": "policy_provider_5", "version": "3.0", "policy_id": "pol_6745"}}, "risk": {"signal": "DENY_SIGNAL", "metadata": {"provider": "risk_provider_4", "version": "3.2", "risk_score": 0.654}}, "approval": {"signal": "DENY_SIGNAL", "metadata": {"provider": "approval_provider_1", "version": "2.4", "workflow_id": "wf_50325"}}, "registry": {"signal": "DENY_SIGNAL", "metadata": {"provider": "registry_provider_2", "version": "2.0", "registry_id": "reg_586"}}, "temporal": {"signal": "DENY_SIGNAL", "metadata": {"provider": "temporal_provider_3", "version": "2.4"}}}}, {"scenario_id": "arm-2-035", "arm": 2, "requester_id": "9a431c2e-e34a-7e86-34a4-95f1b78be019", "action_type": "execute", "resource": "res_1ycl6w1io2u4", "timestamp_utc": "2026-06-20T20:53:12.970730Z", "evidence_sources": {"identity": {"signal": "DENY_SIGNAL", "metadata": {"provider": "identity_provider_2", "version": "3.8"}}, "policy": {"signal": "DENY_SIGNAL", "metadata": {"provider": "policy_provider_1", "version": "3.2", "policy_id": "pol_2525"}}, "risk": {"signal": "DENY_SIGNAL", "metadata": {"provider": "risk_provider_5", "version": "1.2", "risk_score": 0.459}}, "approval": {"signal": "DENY_SIGNAL", "metadata": {"provider": "approval_provider_5", "version": "3.7", "workflow_id": "wf_53847"}}, "registry": {"signal": "DENY_SIGNAL", "metadata": {"provider": "registry_provider_2", "version": "3.1", "registry_id": "reg_578"}}, "temporal": {"signal": "DENY_SIGNAL", "metadata": {"provider": "temporal_provider_5", "version": "3.8"}}}}, {"scenario_id": "arm-2-036", "arm": 2, "requester_id": "ddeeeddd-eefb-3782-b71a-4495c6612931", "action_type": "approve", "resource": "item_6eps27nredlp", "timestamp_utc": "2026-07-02T22:13:12.970759Z", "evidence_sources": {"identity": {"signal": "DENY_SIGNAL", "metadata": {"provider": "identity_provider_2", "version": "2.1"}}, "policy": {"signal": "DENY_SIGNAL", "metadata": {"provider": "policy_provider_5", "version": "1.5", "policy_id": "pol_5873"}}, "risk": {"signal": "DENY_SIGNAL", "metadata": {"provider": "risk_provider_3", "version": "1.2", "risk_score": 0.681}}, "approval": {"signal": "DENY_SIGNAL", "metadata": {"provider": "approval_provider_3", "version": "2.9", "workflow_id": "wf_25940"}}, "registry": {"signal": "DENY_SIGNAL", "metadata": {"provider": "registry_provider_3", "version": "1.5", "registry_id": "reg_542"}}, "temporal": {"signal": "DENY_SIGNAL", "metadata": {"provider": "temporal_provider_1", "version": "1.6"}}}}, {"scenario_id": "arm-2-037", "arm": 2, "requester_id": "caee3ccc-e903-63d1-c232-9e0dbf9fc6ee", "action_type": "transfer", "resource": "obj_m1squez2d2tg", "timestamp_utc": "2026-07-06T12:18:12.970786Z", "evidence_sources": {"identity": {"signal": "DENY_SIGNAL", "metadata": {"provider": "identity_provider_1", "version": "3.6"}}, "policy": {"signal": "DENY_SIGNAL", "metadata": {"provider": "policy_provider_1", "version": "1.1", "policy_id": "pol_8862"}}, "risk": {"signal": "DENY_SIGNAL", "metadata": {"provider": "risk_provider_4", "version": "2.3", "risk_score": 0.546}}, "approval": {"signal": "DENY_SIGNAL", "metadata": {"provider": "approval_provider_2", "version": "3.0", "workflow_id": "wf_49561"}}, "registry": {"signal": "DENY_SIGNAL", "metadata": {"provider": "registry_provider_1", "version": "3.3", "registry_id": "reg_273"}}, "temporal": {"signal": "DENY_SIGNAL", "metadata": {"provider": "temporal_provider_4", "version": "1.3"}}}}, {"scenario_id": "arm-2-038", "arm": 2, "requester_id": "2baa804b-7edd-83dc-300a-6e3d1cafea6f", "action_type": "execute", "resource": "obj_eh5zuxoqlg8r", "timestamp_utc": "2026-06-30T09:02:12.970813Z", "evidence_sources": {"identity": {"signal": "DENY_SIGNAL", "metadata": {"provider": "identity_provider_2", "version": "3.1"}}, "policy": {"signal": "DENY_SIGNAL", "metadata": {"provider": "policy_provider_5", "version": "1.5", "policy_id": "pol_9724"}}, "risk": {"signal": "DENY_SIGNAL", "metadata": {"provider": "risk_provider_5", "version": "2.2", "risk_score": 0.922}}, "approval": {"signal": "DENY_SIGNAL", "metadata": {"provider": "approval_provider_3", "version": "1.2", "workflow_id": "wf_22045"}}, "registry": {"signal": "DENY_SIGNAL", "metadata": {"provider": "registry_provider_3", "version": "1.9", "registry_id": "reg_693"}}, "temporal": {"signal": "DENY_SIGNAL", "metadata": {"provider": "temporal_provider_5", "version": "1.6"}}}}, {"scenario_id": "arm-2-039", "arm": 2, "requester_id": "df4ff371-87cf-fd76-ddee-addbf0defdba", "action_type": "approve", "resource": "res_xt9k8rtz2l0b", "timestamp_utc": "2026-06-30T13:36:12.970842Z", "evidence_sources": {"identity": {"signal": "DENY_SIGNAL", "metadata": {"provider": "identity_provider_4", "version": "3.7"}}, "policy": {"signal": "DENY_SIGNAL", "metadata": {"provider": "policy_provider_3", "version": "1.3", "policy_id": "pol_8060"}}, "risk": {"signal": "DENY_SIGNAL", "metadata": {"provider": "risk_provider_2", "version": "1.1", "risk_score": 0.29}}, "approval": {"signal": "DENY_SIGNAL", "metadata": {"provider": "approval_provider_5", "version": "3.9", "workflow_id": "wf_76121"}}, "registry": {"signal": "DENY_SIGNAL", "metadata": {"provider": "registry_provider_5", "version": "2.3", "registry_id": "reg_627"}}, "temporal": {"signal": "DENY_SIGNAL", "metadata": {"provider": "temporal_provider_5", "version": "2.6"}}}}, {"scenario_id": "arm-2-040", "arm": 2, "requester_id": "26eab0bf-c4ae-8031-5ede-72ca06524081", "action_type": "execute", "resource": "asset_irpo009me0g8", "timestamp_utc": "2026-06-24T04:07:12.970870Z", "evidence_sources": {"identity": {"signal": "DENY_SIGNAL", "metadata": {"provider": "identity_provider_4", "version": "3.1"}}, "policy": {"signal": "DENY_SIGNAL", "metadata": {"provider": "policy_provider_2", "version": "1.5", "policy_id": "pol_4637"}}, "risk": {"signal": "DENY_SIGNAL", "metadata": {"provider": "risk_provider_1", "version": "3.9", "risk_score": 0.151}}, "approval": {"signal": "DENY_SIGNAL", "metadata": {"provider": "approval_provider_5", "version": "3.3", "workflow_id": "wf_56490"}}, "registry": {"signal": "DENY_SIGNAL", "metadata": {"provider": "registry_provider_1", "version": "2.7", "registry_id": "reg_386"}}, "temporal": {"signal": "DENY_SIGNAL", "metadata": {"provider": "temporal_provider_5", "version": "1.7"}}}}, {"scenario_id": "arm-2-041", "arm": 2, "requester_id": "a002b284-d28c-0ee8-c8dc-cc10c643f3a2", "action_type": "execute", "resource": "item_y46omm6mu76v", "timestamp_utc": "2026-06-22T11:52:12.970897Z", "evidence_sources": {"identity": {"signal": "DENY_SIGNAL", "metadata": {"provider": "identity_provider_1", "version": "1.4"}}, "policy": {"signal": "DENY_SIGNAL", "metadata": {"provider": "policy_provider_2", "version": "3.2", "policy_id": "pol_3162"}}, "risk": {"signal": "DENY_SIGNAL", "metadata": {"provider": "risk_provider_1", "version": "3.8", "risk_score": 0.798}}, "approval": {"signal": "DENY_SIGNAL", "metadata": {"provider": "approval_provider_2", "version": "1.8", "workflow_id": "wf_47809"}}, "registry": {"signal": "DENY_SIGNAL", "metadata": {"provider": "registry_provider_3", "version": "3.5", "registry_id": "reg_536"}}, "temporal": {"signal": "DENY_SIGNAL", "metadata": {"provider": "temporal_provider_1", "version": "1.4"}}}}, {"scenario_id": "arm-2-042", "arm": 2, "requester_id": "075bbfd4-9eb9-c055-74dd-eacbff19ebb4", "action_type": "execute", "resource": "res_x0n4l8btktns", "timestamp_utc": "2026-07-01T07:58:12.970923Z", "evidence_sources": {"identity": {"signal": "DENY_SIGNAL", "metadata": {"provider": "identity_provider_3", "version": "2.3"}}, "policy": {"signal": "DENY_SIGNAL", "metadata": {"provider": "policy_provider_2", "version": "3.3", "policy_id": "pol_9424"}}, "risk": {"signal": "DENY_SIGNAL", "metadata": {"provider": "risk_provider_5", "version": "1.9", "risk_score": 0.923}}, "approval": {"signal": "DENY_SIGNAL", "metadata": {"provider": "approval_provider_2", "version": "2.5", "workflow_id": "wf_45368"}}, "registry": {"signal": "DENY_SIGNAL", "metadata": {"provider": "registry_provider_5", "version": "2.0", "registry_id": "reg_599"}}, "temporal": {"signal": "DENY_SIGNAL", "metadata": {"provider": "temporal_provider_4", "version": "1.6"}}}}, {"scenario_id": "arm-2-043", "arm": 2, "requester_id": "1a7cbb00-b76b-fedf-c89c-075f4b4af938", "action_type": "execute", "resource": "res_zsii2fevk5eb", "timestamp_utc": "2026-07-10T00:36:12.970950Z", "evidence_sources": {"identity": {"signal": "DENY_SIGNAL", "metadata": {"provider": "identity_provider_3", "version": "1.1"}}, "policy": {"signal": "DENY_SIGNAL", "metadata": {"provider": "policy_provider_1", "version": "3.5", "policy_id": "pol_2509"}}, "risk": {"signal": "DENY_SIGNAL", "metadata": {"provider": "risk_provider_3", "version": "1.8", "risk_score": 0.095}}, "approval": {"signal": "DENY_SIGNAL", "metadata": {"provider": "approval_provider_3", "version": "2.0", "workflow_id": "wf_56944"}}, "registry": {"signal": "DENY_SIGNAL", "metadata": {"provider": "registry_provider_5", "version": "1.7", "registry_id": "reg_425"}}, "temporal": {"signal": "DENY_SIGNAL", "metadata": {"provider": "temporal_provider_4", "version": "3.7"}}}}, {"scenario_id": "arm-2-044", "arm": 2, "requester_id": "dc4dd18a-ac36-4e16-f03f-dad58d0c0d7a", "action_type": "execute", "resource": "res_zx9md4fvryqh", "timestamp_utc": "2026-07-11T07:33:12.970977Z", "evidence_sources": {"identity": {"signal": "DENY_SIGNAL", "metadata": {"provider": "identity_provider_5", "version": "1.1"}}, "policy": {"signal": "DENY_SIGNAL", "metadata": {"provider": "policy_provider_4", "version": "3.6", "policy_id": "pol_5297"}}, "risk": {"signal": "DENY_SIGNAL", "metadata": {"provider": "risk_provider_2", "version": "2.9", "risk_score": 0.848}}, "approval": {"signal": "DENY_SIGNAL", "metadata": {"provider": "approval_provider_4", "version": "1.9", "workflow_id": "wf_61348"}}, "registry": {"signal": "DENY_SIGNAL", "metadata": {"provider": "registry_provider_1", "version": "1.2", "registry_id": "reg_961"}}, "temporal": {"signal": "DENY_SIGNAL", "metadata": {"provider": "temporal_provider_3", "version": "1.9"}}}}, {"scenario_id": "arm-2-045", "arm": 2, "requester_id": "bb95d3cc-f0ce-557c-7a8c-56c7fb4afdac", "action_type": "delegate", "resource": "obj_0svydqcc0rvo", "timestamp_utc": "2026-06-29T23:54:12.971004Z", "evidence_sources": {"identity": {"signal": "DENY_SIGNAL", "metadata": {"provider": "identity_provider_1", "version": "2.8"}}, "policy": {"signal": "DENY_SIGNAL", "metadata": {"provider": "policy_provider_5", "version": "3.8", "policy_id": "pol_7242"}}, "risk": {"signal": "DENY_SIGNAL", "metadata": {"provider": "risk_provider_4", "version": "3.1", "risk_score": 0.91}}, "approval": {"signal": "DENY_SIGNAL", "metadata": {"provider": "approval_provider_3", "version": "2.9", "workflow_id": "wf_31249"}}, "registry": {"signal": "DENY_SIGNAL", "metadata": {"provider": "registry_provider_5", "version": "2.6", "registry_id": "reg_694"}}, "temporal": {"signal": "DENY_SIGNAL", "metadata": {"provider": "temporal_provider_1", "version": "1.5"}}}}, {"scenario_id": "arm-2-046", "arm": 2, "requester_id": "dbc3a1ec-fcba-bab8-92eb-ee08ff886fe1", "action_type": "approve", "resource": "item_c9t5zgoaqrgl", "timestamp_utc": "2026-07-05T22:08:12.971030Z", "evidence_sources": {"identity": {"signal": "DENY_SIGNAL", "metadata": {"provider": "identity_provider_5", "version": "1.3"}}, "policy": {"signal": "DENY_SIGNAL", "metadata": {"provider": "policy_provider_5", "version": "2.7", "policy_id": "pol_5922"}}, "risk": {"signal": "DENY_SIGNAL", "metadata": {"provider": "risk_provider_5", "version": "2.4", "risk_score": 0.636}}, "approval": {"signal": "DENY_SIGNAL", "metadata": {"provider": "approval_provider_5", "version": "1.5", "workflow_id": "wf_81795"}}, "registry": {"signal": "DENY_SIGNAL", "metadata": {"provider": "registry_provider_2", "version": "3.9", "registry_id": "reg_741"}}, "temporal": {"signal": "DENY_SIGNAL", "metadata": {"provider": "temporal_provider_2", "version": "3.3"}}}}, {"scenario_id": "arm-2-047", "arm": 2, "requester_id": "0e22ac49-c2bc-bd27-f69d-cd0aa4abc2e5", "action_type": "revoke", "resource": "obj_4tigzs4pg0e8", "timestamp_utc": "2026-06-25T18:05:12.971057Z", "evidence_sources": {"identity": {"signal": "DENY_SIGNAL", "metadata": {"provider": "identity_provider_4", "version": "3.3"}}, "policy": {"signal": "DENY_SIGNAL", "metadata": {"provider": "policy_provider_2", "version": "2.6", "policy_id": "pol_1153"}}, "risk": {"signal": "DENY_SIGNAL", "metadata": {"provider": "risk_provider_4", "version": "3.2", "risk_score": 0.879}}, "approval": {"signal": "DENY_SIGNAL", "metadata": {"provider": "approval_provider_3", "version": "2.3", "workflow_id": "wf_54904"}}, "registry": {"signal": "DENY_SIGNAL", "metadata": {"provider": "registry_provider_5", "version": "1.0", "registry_id": "reg_271"}}, "temporal": {"signal": "DENY_SIGNAL", "metadata": {"provider": "temporal_provider_2", "version": "2.2"}}}}, {"scenario_id": "arm-2-048", "arm": 2, "requester_id": "13c2428b-0fd4-1aef-dbae-dfaac671b0af", "action_type": "delegate", "resource": "obj_usa6tl9qtwuc", "timestamp_utc": "2026-07-02T14:24:12.971083Z", "evidence_sources": {"identity": {"signal": "DENY_SIGNAL", "metadata": {"provider": "identity_provider_4", "version": "3.4"}}, "policy": {"signal": "DENY_SIGNAL", "metadata": {"provider": "policy_provider_1", "version": "3.6", "policy_id": "pol_6829"}}, "risk": {"signal": "DENY_SIGNAL", "metadata": {"provider": "risk_provider_1", "version": "1.0", "risk_score": 0.256}}, "approval": {"signal": "DENY_SIGNAL", "metadata": {"provider": "approval_provider_1", "version": "2.5", "workflow_id": "wf_61084"}}, "registry": {"signal": "DENY_SIGNAL", "metadata": {"provider": "registry_provider_3", "version": "3.7", "registry_id": "reg_131"}}, "temporal": {"signal": "DENY_SIGNAL", "metadata": {"provider": "temporal_provider_5", "version": "1.4"}}}}, {"scenario_id": "arm-2-049", "arm": 2, "requester_id": "54e0fd6b-2234-6f1e-ff08-74f6bfaadd3a", "action_type": "execute", "resource": "res_0v3rn650qmmf", "timestamp_utc": "2026-07-12T05:38:12.971111Z", "evidence_sources": {"identity": {"signal": "DENY_SIGNAL", "metadata": {"provider": "identity_provider_5", "version": "2.0"}}, "policy": {"signal": "DENY_SIGNAL", "metadata": {"provider": "policy_provider_4", "version": "2.2", "policy_id": "pol_2112"}}, "risk": {"signal": "DENY_SIGNAL", "metadata": {"provider": "risk_provider_5", "version": "2.5", "risk_score": 0.372}}, "approval": {"signal": "DENY_SIGNAL", "metadata": {"provider": "approval_provider_4", "version": "3.8", "workflow_id": "wf_50549"}}, "registry": {"signal": "DENY_SIGNAL", "metadata": {"provider": "registry_provider_1", "version": "3.8", "registry_id": "reg_905"}}, "temporal": {"signal": "DENY_SIGNAL", "metadata": {"provider": "temporal_provider_5", "version": "1.5"}}}}, {"scenario_id": "arm-2-050", "arm": 2, "requester_id": "b03ee778-0ad8-3abf-bee1-fe9fd4506cf3", "action_type": "delegate", "resource": "res_kec29vr8uw4e", "timestamp_utc": "2026-06-30T03:34:12.971138Z", "evidence_sources": {"identity": {"signal": "DENY_SIGNAL", "metadata": {"provider": "identity_provider_1", "version": "3.5"}}, "policy": {"signal": "DENY_SIGNAL", "metadata": {"provider": "policy_provider_3", "version": "3.2", "policy_id": "pol_4981"}}, "risk": {"signal": "DENY_SIGNAL", "metadata": {"provider": "risk_provider_5", "version": "1.7", "risk_score": 0.504}}, "approval": {"signal": "DENY_SIGNAL", "metadata": {"provider": "approval_provider_5", "version": "2.0", "workflow_id": "wf_32248"}}, "registry": {"signal": "DENY_SIGNAL", "metadata": {"provider": "registry_provider_5", "version": "2.4", "registry_id": "reg_120"}}, "temporal": {"signal": "DENY_SIGNAL", "metadata": {"provider": "temporal_provider_2", "version": "3.5"}}}}, {"scenario_id": "arm-2-051", "arm": 2, "requester_id": "8f43fb64-dfd3-0b55-1db3-a55bc44fee9c", "action_type": "revoke", "resource": "item_9lmx9ixvzy5j", "timestamp_utc": "2026-07-05T03:45:12.971196Z", "evidence_sources": {"identity": {"signal": "DENY_SIGNAL", "metadata": {"provider": "identity_provider_3", "version": "2.8"}}, "policy": {"signal": "DENY_SIGNAL", "metadata": {"provider": "policy_provider_5", "version": "3.6", "policy_id": "pol_2614"}}, "risk": {"signal": "DENY_SIGNAL", "metadata": {"provider": "risk_provider_3", "version": "2.5", "risk_score": 0.256}}, "approval": {"signal": "DENY_SIGNAL", "metadata": {"provider": "approval_provider_3", "version": "1.6", "workflow_id": "wf_50915"}}, "registry": {"signal": "DENY_SIGNAL", "metadata": {"provider": "registry_provider_4", "version": "1.2", "registry_id": "reg_473"}}, "temporal": {"signal": "DENY_SIGNAL", "metadata": {"provider": "temporal_provider_5", "version": "1.9"}}}}, {"scenario_id": "arm-2-052", "arm": 2, "requester_id": "df0c52db-b5ad-b547-0d2b-90c9adffe2cd", "action_type": "approve", "resource": "res_0dbip1arco0w", "timestamp_utc": "2026-06-28T07:23:12.971236Z", "evidence_sources": {"identity": {"signal": "DENY_SIGNAL", "metadata": {"provider": "identity_provider_1", "version": "2.3"}}, "policy": {"signal": "DENY_SIGNAL", "metadata": {"provider": "policy_provider_1", "version": "3.8", "policy_id": "pol_9164"}}, "risk": {"signal": "DENY_SIGNAL", "metadata": {"provider": "risk_provider_4", "version": "1.3", "risk_score": 0.346}}, "approval": {"signal": "DENY_SIGNAL", "metadata": {"provider": "approval_provider_4", "version": "1.5", "workflow_id": "wf_36830"}}, "registry": {"signal": "DENY_SIGNAL", "metadata": {"provider": "registry_provider_5", "version": "2.5", "registry_id": "reg_891"}}, "temporal": {"signal": "DENY_SIGNAL", "metadata": {"provider": "temporal_provider_4", "version": "1.0"}}}}, {"scenario_id": "arm-2-053", "arm": 2, "requester_id": "bdb816fd-ebc7-fa8a-fbd4-e6c802c378e0", "action_type": "transfer", "resource": "item_nlovcf1498ri", "timestamp_utc": "2026-06-22T22:04:12.971264Z", "evidence_sources": {"identity": {"signal": "DENY_SIGNAL", "metadata": {"provider": "identity_provider_4", "version": "2.6"}}, "policy": {"signal": "DENY_SIGNAL", "metadata": {"provider": "policy_provider_5", "version": "1.7", "policy_id": "pol_5655"}}, "risk": {"signal": "DENY_SIGNAL", "metadata": {"provider": "risk_provider_1", "version": "3.3", "risk_score": 0.13}}, "approval": {"signal": "DENY_SIGNAL", "metadata": {"provider": "approval_provider_4", "version": "2.1", "workflow_id": "wf_20649"}}, "registry": {"signal": "DENY_SIGNAL", "metadata": {"provider": "registry_provider_3", "version": "1.7", "registry_id": "reg_122"}}, "temporal": {"signal": "DENY_SIGNAL", "metadata": {"provider": "temporal_provider_3", "version": "2.8"}}}}, {"scenario_id": "arm-2-054", "arm": 2, "requester_id": "f80d8eb0-aecd-bd1b-a195-fe7ca5a3a8b6", "action_type": "revoke", "resource": "res_djtrpw6vsp9k", "timestamp_utc": "2026-06-18T18:19:12.971291Z", "evidence_sources": {"identity": {"signal": "DENY_SIGNAL", "metadata": {"provider": "identity_provider_3", "version": "1.6"}}, "policy": {"signal": "DENY_SIGNAL", "metadata": {"provider": "policy_provider_4", "version": "3.0", "policy_id": "pol_6115"}}, "risk": {"signal": "DENY_SIGNAL", "metadata": {"provider": "risk_provider_1", "version": "3.1", "risk_score": 0.136}}, "approval": {"signal": "DENY_SIGNAL", "metadata": {"provider": "approval_provider_2", "version": "1.1", "workflow_id": "wf_53658"}}, "registry": {"signal": "DENY_SIGNAL", "metadata": {"provider": "registry_provider_4", "version": "3.2", "registry_id": "reg_379"}}, "temporal": {"signal": "DENY_SIGNAL", "metadata": {"provider": "temporal_provider_2", "version": "3.6"}}}}, {"scenario_id": "arm-2-055", "arm": 2, "requester_id": "a98b2fb0-d82b-32f5-6fdb-ba4916d5f7c8", "action_type": "approve", "resource": "obj_gqmmj2ky015r", "timestamp_utc": "2026-06-29T07:31:12.971366Z", "evidence_sources": {"identity": {"signal": "DENY_SIGNAL", "metadata": {"provider": "identity_provider_4", "version": "3.5"}}, "policy": {"signal": "DENY_SIGNAL", "metadata": {"provider": "policy_provider_5", "version": "2.3", "policy_id": "pol_1642"}}, "risk": {"signal": "DENY_SIGNAL", "metadata": {"provider": "risk_provider_3", "version": "3.0", "risk_score": 0.169}}, "approval": {"signal": "DENY_SIGNAL", "metadata": {"provider": "approval_provider_1", "version": "2.9", "workflow_id": "wf_96023"}}, "registry": {"signal": "DENY_SIGNAL", "metadata": {"provider": "registry_provider_2", "version": "3.3", "registry_id": "reg_845"}}, "temporal": {"signal": "DENY_SIGNAL", "metadata": {"provider": "temporal_provider_1", "version": "3.2"}}}}, {"scenario_id": "arm-2-056", "arm": 2, "requester_id": "dfa2b9db-4679-f7c6-e8fe-cbeb129fe851", "action_type": "revoke", "resource": "res_jjor70c2yadt", "timestamp_utc": "2026-06-30T03:09:12.971394Z", "evidence_sources": {"identity": {"signal": "DENY_SIGNAL", "metadata": {"provider": "identity_provider_1", "version": "1.3"}}, "policy": {"signal": "DENY_SIGNAL", "metadata": {"provider": "policy_provider_4", "version": "3.6", "policy_id": "pol_6978"}}, "risk": {"signal": "DENY_SIGNAL", "metadata": {"provider": "risk_provider_1", "version": "1.2", "risk_score": 0.383}}, "approval": {"signal": "DENY_SIGNAL", "metadata": {"provider": "approval_provider_1", "version": "2.6", "workflow_id": "wf_49409"}}, "registry": {"signal": "DENY_SIGNAL", "metadata": {"provider": "registry_provider_3", "version": "2.7", "registry_id": "reg_459"}}, "temporal": {"signal": "DENY_SIGNAL", "metadata": {"provider": "temporal_provider_3", "version": "1.1"}}}}, {"scenario_id": "arm-2-057", "arm": 2, "requester_id": "cc20ae1f-eefe-00de-f82d-eaad3f95d66c", "action_type": "approve", "resource": "asset_777duczizk2x", "timestamp_utc": "2026-07-07T13:46:12.971421Z", "evidence_sources": {"identity": {"signal": "DENY_SIGNAL", "metadata": {"provider": "identity_provider_2", "version": "3.5"}}, "policy": {"signal": "DENY_SIGNAL", "metadata": {"provider": "policy_provider_3", "version": "1.3", "policy_id": "pol_9107"}}, "risk": {"signal": "DENY_SIGNAL", "metadata": {"provider": "risk_provider_3", "version": "1.7", "risk_score": 0.566}}, "approval": {"signal": "DENY_SIGNAL", "metadata": {"provider": "approval_provider_2", "version": "2.4", "workflow_id": "wf_58432"}}, "registry": {"signal": "DENY_SIGNAL", "metadata": {"provider": "registry_provider_1", "version": "1.0", "registry_id": "reg_461"}}, "temporal": {"signal": "DENY_SIGNAL", "metadata": {"provider": "temporal_provider_4", "version": "1.7"}}}}, {"scenario_id": "arm-2-058", "arm": 2, "requester_id": "ec9deabc-7ef7-d988-54ec-fda9f9db6ffe", "action_type": "execute", "resource": "item_opuyxcmvs0qv", "timestamp_utc": "2026-06-23T07:27:12.971448Z", "evidence_sources": {"identity": {"signal": "DENY_SIGNAL", "metadata": {"provider": "identity_provider_3", "version": "2.5"}}, "policy": {"signal": "DENY_SIGNAL", "metadata": {"provider": "policy_provider_2", "version": "3.1", "policy_id": "pol_7476"}}, "risk": {"signal": "DENY_SIGNAL", "metadata": {"provider": "risk_provider_5", "version": "3.0", "risk_score": 0.256}}, "approval": {"signal": "DENY_SIGNAL", "metadata": {"provider": "approval_provider_1", "version": "1.7", "workflow_id": "wf_91508"}}, "registry": {"signal": "DENY_SIGNAL", "metadata": {"provider": "registry_provider_3", "version": "1.8", "registry_id": "reg_877"}}, "temporal": {"signal": "DENY_SIGNAL", "metadata": {"provider": "temporal_provider_4", "version": "2.9"}}}}, {"scenario_id": "arm-2-059", "arm": 2, "requester_id": "ebe6c7c9-90cc-cf97-fecb-d4c828f5075e", "action_type": "approve", "resource": "item_46c9m5z61b7u", "timestamp_utc": "2026-07-15T08:54:12.971474Z", "evidence_sources": {"identity": {"signal": "DENY_SIGNAL", "metadata": {"provider": "identity_provider_1", "version": "2.4"}}, "policy": {"signal": "DENY_SIGNAL", "metadata": {"provider": "policy_provider_4", "version": "3.8", "policy_id": "pol_8903"}}, "risk": {"signal": "DENY_SIGNAL", "metadata": {"provider": "risk_provider_3", "version": "1.0", "risk_score": 0.265}}, "approval": {"signal": "DENY_SIGNAL", "metadata": {"provider": "approval_provider_5", "version": "3.1", "workflow_id": "wf_91062"}}, "registry": {"signal": "DENY_SIGNAL", "metadata": {"provider": "registry_provider_4", "version": "1.3", "registry_id": "reg_595"}}, "temporal": {"signal": "DENY_SIGNAL", "metadata": {"provider": "temporal_provider_3", "version": "2.2"}}}}, {"scenario_id": "arm-2-060", "arm": 2, "requester_id": "b1dbfe07-f49a-ea70-0dc4-ddc0d19cf4ec", "action_type": "execute", "resource": "obj_rkdhbtf8v692", "timestamp_utc": "2026-06-24T08:29:12.971500Z", "evidence_sources": {"identity": {"signal": "DENY_SIGNAL", "metadata": {"provider": "identity_provider_4", "version": "3.3"}}, "policy": {"signal": "DENY_SIGNAL", "metadata": {"provider": "policy_provider_2", "version": "2.0", "policy_id": "pol_4957"}}, "risk": {"signal": "DENY_SIGNAL", "metadata": {"provider": "risk_provider_2", "version": "3.5", "risk_score": 0.619}}, "approval": {"signal": "DENY_SIGNAL", "metadata": {"provider": "approval_provider_1", "version": "2.4", "workflow_id": "wf_17487"}}, "registry": {"signal": "DENY_SIGNAL", "metadata": {"provider": "registry_provider_2", "version": "1.9", "registry_id": "reg_351"}}, "temporal": {"signal": "DENY_SIGNAL", "metadata": {"provider": "temporal_provider_4", "version": "3.1"}}}}, {"scenario_id": "arm-2-061", "arm": 2, "requester_id": "1ff9be23-bb3a-cdb6-c83f-de0f2eaee97a", "action_type": "transfer", "resource": "res_c44q9ejzf2ek", "timestamp_utc": "2026-07-08T08:31:12.971526Z", "evidence_sources": {"identity": {"signal": "DENY_SIGNAL", "metadata": {"provider": "identity_provider_1", "version": "3.9"}}, "policy": {"signal": "DENY_SIGNAL", "metadata": {"provider": "policy_provider_4", "version": "1.3", "policy_id": "pol_3975"}}, "risk": {"signal": "DENY_SIGNAL", "metadata": {"provider": "risk_provider_2", "version": "3.8", "risk_score": 0.216}}, "approval": {"signal": "DENY_SIGNAL", "metadata": {"provider": "approval_provider_3", "version": "1.9", "workflow_id": "wf_66068"}}, "registry": {"signal": "DENY_SIGNAL", "metadata": {"provider": "registry_provider_4", "version": "1.7", "registry_id": "reg_821"}}, "temporal": {"signal": "DENY_SIGNAL", "metadata": {"provider": "temporal_provider_3", "version": "3.9"}}}}, {"scenario_id": "arm-2-062", "arm": 2, "requester_id": "eb00ebd9-6feb-8aab-c6b8-7eebdf3dcd3e", "action_type": "transfer", "resource": "asset_sdyl7jseho7p", "timestamp_utc": "2026-07-01T08:40:12.971552Z", "evidence_sources": {"identity": {"signal": "DENY_SIGNAL", "metadata": {"provider": "identity_provider_2", "version": "3.3"}}, "policy": {"signal": "DENY_SIGNAL", "metadata": {"provider": "policy_provider_5", "version": "3.5", "policy_id": "pol_6469"}}, "risk": {"signal": "DENY_SIGNAL", "metadata": {"provider": "risk_provider_4", "version": "1.8", "risk_score": 0.778}}, "approval": {"signal": "DENY_SIGNAL", "metadata": {"provider": "approval_provider_5", "version": "2.4", "workflow_id": "wf_79278"}}, "registry": {"signal": "DENY_SIGNAL", "metadata": {"provider": "registry_provider_5", "version": "2.1", "registry_id": "reg_394"}}, "temporal": {"signal": "DENY_SIGNAL", "metadata": {"provider": "temporal_provider_1", "version": "1.4"}}}}, {"scenario_id": "arm-2-063", "arm": 2, "requester_id": "a3dddfa8-c1ca-aa13-aceb-e11e12695a4b", "action_type": "delegate", "resource": "asset_5qt3wh6wy7eb", "timestamp_utc": "2026-06-25T08:03:12.971579Z", "evidence_sources": {"identity": {"signal": "DENY_SIGNAL", "metadata": {"provider": "identity_provider_5", "version": "2.6"}}, "policy": {"signal": "DENY_SIGNAL", "metadata": {"provider": "policy_provider_5", "version": "3.9", "policy_id": "pol_9556"}}, "risk": {"signal": "DENY_SIGNAL", "metadata": {"provider": "risk_provider_5", "version": "1.2", "risk_score": 0.273}}, "approval": {"signal": "DENY_SIGNAL", "metadata": {"provider": "approval_provider_3", "version": "2.1", "workflow_id": "wf_61064"}}, "registry": {"signal": "DENY_SIGNAL", "metadata": {"provider": "registry_provider_4", "version": "2.3", "registry_id": "reg_639"}}, "temporal": {"signal": "DENY_SIGNAL", "metadata": {"provider": "temporal_provider_5", "version": "3.5"}}}}, {"scenario_id": "arm-2-064", "arm": 2, "requester_id": "bdbacd7d-4ad6-c6f0-9cc2-0baaa2c6dfd3", "action_type": "approve", "resource": "res_2yi1nv7ci178", "timestamp_utc": "2026-07-11T08:40:12.971606Z", "evidence_sources": {"identity": {"signal": "DENY_SIGNAL", "metadata": {"provider": "identity_provider_4", "version": "3.1"}}, "policy": {"signal": "DENY_SIGNAL", "metadata": {"provider": "policy_provider_5", "version": "3.1", "policy_id": "pol_7226"}}, "risk": {"signal": "DENY_SIGNAL", "metadata": {"provider": "risk_provider_2", "version": "3.3", "risk_score": 0.128}}, "approval": {"signal": "DENY_SIGNAL", "metadata": {"provider": "approval_provider_1", "version": "1.0", "workflow_id": "wf_18292"}}, "registry": {"signal": "DENY_SIGNAL", "metadata": {"provider": "registry_provider_2", "version": "2.5", "registry_id": "reg_402"}}, "temporal": {"signal": "DENY_SIGNAL", "metadata": {"provider": "temporal_provider_2", "version": "2.5"}}}}, {"scenario_id": "arm-2-065", "arm": 2, "requester_id": "a1b9da1c-e3db-536d-06fa-71853ed3a47e", "action_type": "transfer", "resource": "item_yx8o1ck7fcwh", "timestamp_utc": "2026-07-12T10:38:12.971633Z", "evidence_sources": {"identity": {"signal": "DENY_SIGNAL", "metadata": {"provider": "identity_provider_1", "version": "3.3"}}, "policy": {"signal": "DENY_SIGNAL", "metadata": {"provider": "policy_provider_5", "version": "1.5", "policy_id": "pol_2160"}}, "risk": {"signal": "DENY_SIGNAL", "metadata": {"provider": "risk_provider_2", "version": "2.5", "risk_score": 0.591}}, "approval": {"signal": "DENY_SIGNAL", "metadata": {"provider": "approval_provider_1", "version": "2.7", "workflow_id": "wf_13312"}}, "registry": {"signal": "DENY_SIGNAL", "metadata": {"provider": "registry_provider_4", "version": "3.6", "registry_id": "reg_292"}}, "temporal": {"signal": "DENY_SIGNAL", "metadata": {"provider": "temporal_provider_4", "version": "3.2"}}}}, {"scenario_id": "arm-2-066", "arm": 2, "requester_id": "eebabbfc-ece4-1da6-8b47-2b79cc8d8dcd", "action_type": "approve", "resource": "obj_a41y44kua4q6", "timestamp_utc": "2026-06-27T17:58:12.971659Z", "evidence_sources": {"identity": {"signal": "DENY_SIGNAL", "metadata": {"provider": "identity_provider_2", "version": "2.8"}}, "policy": {"signal": "DENY_SIGNAL", "metadata": {"provider": "policy_provider_5", "version": "2.0", "policy_id": "pol_6665"}}, "risk": {"signal": "DENY_SIGNAL", "metadata": {"provider": "risk_provider_3", "version": "2.1", "risk_score": 0.665}}, "approval": {"signal": "DENY_SIGNAL", "metadata": {"provider": "approval_provider_4", "version": "1.7", "workflow_id": "wf_70660"}}, "registry": {"signal": "DENY_SIGNAL", "metadata": {"provider": "registry_provider_2", "version": "2.3", "registry_id": "reg_124"}}, "temporal": {"signal": "DENY_SIGNAL", "metadata": {"provider": "temporal_provider_2", "version": "1.7"}}}}, {"scenario_id": "arm-2-067", "arm": 2, "requester_id": "12792fc4-b4d4-ddf6-2d96-c52bcaf45bc4", "action_type": "revoke", "resource": "asset_tliw9cif6f7p", "timestamp_utc": "2026-07-17T13:22:12.971686Z", "evidence_sources": {"identity": {"signal": "DENY_SIGNAL", "metadata": {"provider": "identity_provider_5", "version": "2.4"}}, "policy": {"signal": "DENY_SIGNAL", "metadata": {"provider": "policy_provider_2", "version": "2.5", "policy_id": "pol_8747"}}, "risk": {"signal": "DENY_SIGNAL", "metadata": {"provider": "risk_provider_3", "version": "3.5", "risk_score": 0.099}}, "approval": {"signal": "DENY_SIGNAL", "metadata": {"provider": "approval_provider_1", "version": "3.4", "workflow_id": "wf_84815"}}, "registry": {"signal": "DENY_SIGNAL", "metadata": {"provider": "registry_provider_3", "version": "1.9", "registry_id": "reg_550"}}, "temporal": {"signal": "DENY_SIGNAL", "metadata": {"provider": "temporal_provider_2", "version": "1.1"}}}}, {"scenario_id": "arm-2-068", "arm": 2, "requester_id": "dc5a9ba7-72dd-92f0-ef1d-5aa8e8c24a2c", "action_type": "revoke", "resource": "item_qzsgzlxei19p", "timestamp_utc": "2026-06-24T11:19:12.971712Z", "evidence_sources": {"identity": {"signal": "DENY_SIGNAL", "metadata": {"provider": "identity_provider_2", "version": "1.7"}}, "policy": {"signal": "DENY_SIGNAL", "metadata": {"provider": "policy_provider_5", "version": "2.4", "policy_id": "pol_7911"}}, "risk": {"signal": "DENY_SIGNAL", "metadata": {"provider": "risk_provider_5", "version": "2.6", "risk_score": 0.08}}, "approval": {"signal": "DENY_SIGNAL", "metadata": {"provider": "approval_provider_5", "version": "3.7", "workflow_id": "wf_99491"}}, "registry": {"signal": "DENY_SIGNAL", "metadata": {"provider": "registry_provider_5", "version": "1.0", "registry_id": "reg_522"}}, "temporal": {"signal": "DENY_SIGNAL", "metadata": {"provider": "temporal_provider_2", "version": "1.7"}}}}, {"scenario_id": "arm-2-069", "arm": 2, "requester_id": "5ca4d937-debb-4e2e-ff14-1df8efae30fe", "action_type": "delegate", "resource": "res_fsmgq2dggeff", "timestamp_utc": "2026-06-28T21:05:12.971739Z", "evidence_sources": {"identity": {"signal": "DENY_SIGNAL", "metadata": {"provider": "identity_provider_1", "version": "2.9"}}, "policy": {"signal": "DENY_SIGNAL", "metadata": {"provider": "policy_provider_1", "version": "3.4", "policy_id": "pol_2581"}}, "risk": {"signal": "DENY_SIGNAL", "metadata": {"provider": "risk_provider_3", "version": "2.9", "risk_score": 0.656}}, "approval": {"signal": "DENY_SIGNAL", "metadata": {"provider": "approval_provider_3", "version": "2.1", "workflow_id": "wf_67883"}}, "registry": {"signal": "DENY_SIGNAL", "metadata": {"provider": "registry_provider_3", "version": "2.3", "registry_id": "reg_443"}}, "temporal": {"signal": "DENY_SIGNAL", "metadata": {"provider": "temporal_provider_3", "version": "3.0"}}}}, {"scenario_id": "arm-2-070", "arm": 2, "requester_id": "c0449e83-f8dd-befe-61cb-bfad3d5ebc3e", "action_type": "execute", "resource": "asset_r6c8dpztefev", "timestamp_utc": "2026-07-03T23:22:12.971766Z", "evidence_sources": {"identity": {"signal": "DENY_SIGNAL", "metadata": {"provider": "identity_provider_5", "version": "1.2"}}, "policy": {"signal": "DENY_SIGNAL", "metadata": {"provider": "policy_provider_4", "version": "2.5", "policy_id": "pol_1178"}}, "risk": {"signal": "DENY_SIGNAL", "metadata": {"provider": "risk_provider_3", "version": "1.4", "risk_score": 0.754}}, "approval": {"signal": "DENY_SIGNAL", "metadata": {"provider": "approval_provider_5", "version": "1.1", "workflow_id": "wf_30803"}}, "registry": {"signal": "DENY_SIGNAL", "metadata": {"provider": "registry_provider_1", "version": "1.2", "registry_id": "reg_207"}}, "temporal": {"signal": "DENY_SIGNAL", "metadata": {"provider": "temporal_provider_1", "version": "3.4"}}}}, {"scenario_id": "arm-2-071", "arm": 2, "requester_id": "7e11f476-1c52-fb53-a1c6-f4805b9b24fd", "action_type": "revoke", "resource": "res_tqz4uduaompv", "timestamp_utc": "2026-06-20T13:00:12.971793Z", "evidence_sources": {"identity": {"signal": "DENY_SIGNAL", "metadata": {"provider": "identity_provider_5", "version": "3.0"}}, "policy": {"signal": "DENY_SIGNAL", "metadata": {"provider": "policy_provider_4", "version": "3.2", "policy_id": "pol_5139"}}, "risk": {"signal": "DENY_SIGNAL", "metadata": {"provider": "risk_provider_5", "version": "3.5", "risk_score": 0.116}}, "approval": {"signal": "DENY_SIGNAL", "metadata": {"provider": "approval_provider_2", "version": "2.7", "workflow_id": "wf_70903"}}, "registry": {"signal": "DENY_SIGNAL", "metadata": {"provider": "registry_provider_2", "version": "3.4", "registry_id": "reg_442"}}, "temporal": {"signal": "DENY_SIGNAL", "metadata": {"provider": "temporal_provider_3", "version": "2.9"}}}}, {"scenario_id": "arm-2-072", "arm": 2, "requester_id": "8089b5a3-5de6-ce4a-4bee-287fc59af1fa", "action_type": "transfer", "resource": "obj_14lxeg6b80vf", "timestamp_utc": "2026-07-12T06:46:12.971818Z", "evidence_sources": {"identity": {"signal": "DENY_SIGNAL", "metadata": {"provider": "identity_provider_5", "version": "2.6"}}, "policy": {"signal": "DENY_SIGNAL", "metadata": {"provider": "policy_provider_3", "version": "2.5", "policy_id": "pol_4121"}}, "risk": {"signal": "DENY_SIGNAL", "metadata": {"provider": "risk_provider_5", "version": "2.8", "risk_score": 0.012}}, "approval": {"signal": "DENY_SIGNAL", "metadata": {"provider": "approval_provider_3", "version": "2.3", "workflow_id": "wf_17214"}}, "registry": {"signal": "DENY_SIGNAL", "metadata": {"provider": "registry_provider_4", "version": "2.1", "registry_id": "reg_679"}}, "temporal": {"signal": "DENY_SIGNAL", "metadata": {"provider": "temporal_provider_2", "version": "1.9"}}}}, {"scenario_id": "arm-2-073", "arm": 2, "requester_id": "aedbcaf6-bae0-9f54-08ea-f1afd726dbc9", "action_type": "execute", "resource": "obj_np82be3k5sur", "timestamp_utc": "2026-07-01T23:25:12.971844Z", "evidence_sources": {"identity": {"signal": "DENY_SIGNAL", "metadata": {"provider": "identity_provider_3", "version": "1.1"}}, "policy": {"signal": "DENY_SIGNAL", "metadata": {"provider": "policy_provider_1", "version": "1.1", "policy_id": "pol_2155"}}, "risk": {"signal": "DENY_SIGNAL", "metadata": {"provider": "risk_provider_1", "version": "2.8", "risk_score": 0.231}}, "approval": {"signal": "DENY_SIGNAL", "metadata": {"provider": "approval_provider_2", "version": "1.7", "workflow_id": "wf_43599"}}, "registry": {"signal": "DENY_SIGNAL", "metadata": {"provider": "registry_provider_5", "version": "1.9", "registry_id": "reg_107"}}, "temporal": {"signal": "DENY_SIGNAL", "metadata": {"provider": "temporal_provider_2", "version": "3.6"}}}}, {"scenario_id": "arm-2-074", "arm": 2, "requester_id": "ae28ca2c-5da6-67fa-163b-6a7b3d3cc006", "action_type": "approve", "resource": "item_kh5cahe9rfm7", "timestamp_utc": "2026-06-17T09:28:12.971871Z", "evidence_sources": {"identity": {"signal": "DENY_SIGNAL", "metadata": {"provider": "identity_provider_1", "version": "2.0"}}, "policy": {"signal": "DENY_SIGNAL", "metadata": {"provider": "policy_provider_3", "version": "2.1", "policy_id": "pol_8061"}}, "risk": {"signal": "DENY_SIGNAL", "metadata": {"provider": "risk_provider_1", "version": "1.7", "risk_score": 0.504}}, "approval": {"signal": "DENY_SIGNAL", "metadata": {"provider": "approval_provider_5", "version": "1.4", "workflow_id": "wf_69796"}}, "registry": {"signal": "DENY_SIGNAL", "metadata": {"provider": "registry_provider_1", "version": "1.3", "registry_id": "reg_100"}}, "temporal": {"signal": "DENY_SIGNAL", "metadata": {"provider": "temporal_provider_1", "version": "2.7"}}}}, {"scenario_id": "arm-2-075", "arm": 2, "requester_id": "cb2da7b6-e6db-c8f2-a82e-b0a93b5eb9e7", "action_type": "transfer", "resource": "asset_rp992wc38tul", "timestamp_utc": "2026-06-26T14:51:12.971891Z", "evidence_sources": {"identity": {"signal": "DENY_SIGNAL", "metadata": {"provider": "identity_provider_3", "version": "2.4"}}, "policy": {"signal": "DENY_SIGNAL", "metadata": {"provider": "policy_provider_4", "version": "3.5", "policy_id": "pol_6690"}}, "risk": {"signal": "DENY_SIGNAL", "metadata": {"provider": "risk_provider_3", "version": "3.3", "risk_score": 0.956}}, "approval": {"signal": "DENY_SIGNAL", "metadata": {"provider": "approval_provider_1", "version": "2.6", "workflow_id": "wf_36240"}}, "registry": {"signal": "DENY_SIGNAL", "metadata": {"provider": "registry_provider_1", "version": "2.9", "registry_id": "reg_536"}}, "temporal": {"signal": "DENY_SIGNAL", "metadata": {"provider": "temporal_provider_3", "version": "2.6"}}}}, {"scenario_id": "arm-2-076", "arm": 2, "requester_id": "ca84fea5-2ea8-55cd-9b4f-f416edc6b7b4", "action_type": "approve", "resource": "asset_lq0ab3o3esu1", "timestamp_utc": "2026-06-23T03:17:12.971911Z", "evidence_sources": {"identity": {"signal": "DENY_SIGNAL", "metadata": {"provider": "identity_provider_5", "version": "1.8"}}, "policy": {"signal": "DENY_SIGNAL", "metadata": {"provider": "policy_provider_2", "version": "3.5", "policy_id": "pol_5895"}}, "risk": {"signal": "DENY_SIGNAL", "metadata": {"provider": "risk_provider_5", "version": "3.8", "risk_score": 0.524}}, "approval": {"signal": "DENY_SIGNAL", "metadata": {"provider": "approval_provider_5", "version": "2.0", "workflow_id": "wf_22948"}}, "registry": {"signal": "DENY_SIGNAL", "metadata": {"provider": "registry_provider_3", "version": "1.6", "registry_id": "reg_138"}}, "temporal": {"signal": "DENY_SIGNAL", "metadata": {"provider": "temporal_provider_4", "version": "1.0"}}}}, {"scenario_id": "arm-2-077", "arm": 2, "requester_id": "df9fe1c0-deb1-b19f-ddd8-34aa8d2e0684", "action_type": "execute", "resource": "obj_60xyr27a9xeu", "timestamp_utc": "2026-07-06T23:49:12.971930Z", "evidence_sources": {"identity": {"signal": "DENY_SIGNAL", "metadata": {"provider": "identity_provider_3", "version": "1.1"}}, "policy": {"signal": "DENY_SIGNAL", "metadata": {"provider": "policy_provider_4", "version": "3.1", "policy_id": "pol_5182"}}, "risk": {"signal": "DENY_SIGNAL", "metadata": {"provider": "risk_provider_5", "version": "1.7", "risk_score": 0.814}}, "approval": {"signal": "DENY_SIGNAL", "metadata": {"provider": "approval_provider_1", "version": "2.5", "workflow_id": "wf_68699"}}, "registry": {"signal": "DENY_SIGNAL", "metadata": {"provider": "registry_provider_5", "version": "3.6", "registry_id": "reg_179"}}, "temporal": {"signal": "DENY_SIGNAL", "metadata": {"provider": "temporal_provider_5", "version": "3.1"}}}}, {"scenario_id": "arm-2-078", "arm": 2, "requester_id": "edae688c-c61d-99be-26ca-a64b60bcbef4", "action_type": "revoke", "resource": "asset_cyj352zwy9bu", "timestamp_utc": "2026-06-30T06:24:12.971949Z", "evidence_sources": {"identity": {"signal": "DENY_SIGNAL", "metadata": {"provider": "identity_provider_2", "version": "1.5"}}, "policy": {"signal": "DENY_SIGNAL", "metadata": {"provider": "policy_provider_3", "version": "1.2", "policy_id": "pol_8833"}}, "risk": {"signal": "DENY_SIGNAL", "metadata": {"provider": "risk_provider_2", "version": "3.0", "risk_score": 0.78}}, "approval": {"signal": "DENY_SIGNAL", "metadata": {"provider": "approval_provider_3", "version": "3.3", "workflow_id": "wf_30221"}}, "registry": {"signal": "DENY_SIGNAL", "metadata": {"provider": "registry_provider_3", "version": "3.1", "registry_id": "reg_979"}}, "temporal": {"signal": "DENY_SIGNAL", "metadata": {"provider": "temporal_provider_1", "version": "3.3"}}}}, {"scenario_id": "arm-2-079", "arm": 2, "requester_id": "14d924a1-3abd-cabf-b1ac-e779c06b16f4", "action_type": "transfer", "resource": "item_a9j17xuiku1z", "timestamp_utc": "2026-06-25T23:54:12.971969Z", "evidence_sources": {"identity": {"signal": "DENY_SIGNAL", "metadata": {"provider": "identity_provider_2", "version": "2.2"}}, "policy": {"signal": "DENY_SIGNAL", "metadata": {"provider": "policy_provider_3", "version": "2.0", "policy_id": "pol_7964"}}, "risk": {"signal": "DENY_SIGNAL", "metadata": {"provider": "risk_provider_4", "version": "2.3", "risk_score": 0.543}}, "approval": {"signal": "DENY_SIGNAL", "metadata": {"provider": "approval_provider_5", "version": "3.4", "workflow_id": "wf_58022"}}, "registry": {"signal": "DENY_SIGNAL", "metadata": {"provider": "registry_provider_4", "version": "2.1", "registry_id": "reg_866"}}, "temporal": {"signal": "DENY_SIGNAL", "metadata": {"provider": "temporal_provider_4", "version": "3.6"}}}}, {"scenario_id": "arm-2-080", "arm": 2, "requester_id": "3f486bcd-ddfd-de6b-ed4d-daafccd8b2bf", "action_type": "delegate", "resource": "asset_98zkq83rvdfh", "timestamp_utc": "2026-07-08T16:18:12.971988Z", "evidence_sources": {"identity": {"signal": "DENY_SIGNAL", "metadata": {"provider": "identity_provider_3", "version": "3.8"}}, "policy": {"signal": "DENY_SIGNAL", "metadata": {"provider": "policy_provider_5", "version": "2.5", "policy_id": "pol_3997"}}, "risk": {"signal": "DENY_SIGNAL", "metadata": {"provider": "risk_provider_2", "version": "3.9", "risk_score": 0.998}}, "approval": {"signal": "DENY_SIGNAL", "metadata": {"provider": "approval_provider_2", "version": "1.3", "workflow_id": "wf_38436"}}, "registry": {"signal": "DENY_SIGNAL", "metadata": {"provider": "registry_provider_5", "version": "1.0", "registry_id": "reg_888"}}, "temporal": {"signal": "DENY_SIGNAL", "metadata": {"provider": "temporal_provider_4", "version": "1.7"}}}}, {"scenario_id": "arm-2-081", "arm": 2, "requester_id": "ae4fdf49-6ce6-da06-5efb-6ac1ba9b3b2f", "action_type": "revoke", "resource": "item_pvljcxm3uzxw", "timestamp_utc": "2026-06-29T09:02:12.972007Z", "evidence_sources": {"identity": {"signal": "DENY_SIGNAL", "metadata": {"provider": "identity_provider_1", "version": "1.5"}}, "policy": {"signal": "DENY_SIGNAL", "metadata": {"provider": "policy_provider_2", "version": "3.3", "policy_id": "pol_2207"}}, "risk": {"signal": "DENY_SIGNAL", "metadata": {"provider": "risk_provider_5", "version": "3.7", "risk_score": 0.274}}, "approval": {"signal": "DENY_SIGNAL", "metadata": {"provider": "approval_provider_5", "version": "2.5", "workflow_id": "wf_27736"}}, "registry": {"signal": "DENY_SIGNAL", "metadata": {"provider": "registry_provider_4", "version": "1.8", "registry_id": "reg_748"}}, "temporal": {"signal": "DENY_SIGNAL", "metadata": {"provider": "temporal_provider_5", "version": "1.2"}}}}, {"scenario_id": "arm-2-082", "arm": 2, "requester_id": "3fb78714-6600-a5ad-17af-9fe3a85e02cf", "action_type": "approve", "resource": "obj_9q8jfqe473b0", "timestamp_utc": "2026-06-30T03:25:12.972027Z", "evidence_sources": {"identity": {"signal": "DENY_SIGNAL", "metadata": {"provider": "identity_provider_1", "version": "1.0"}}, "policy": {"signal": "DENY_SIGNAL", "metadata": {"provider": "policy_provider_3", "version": "3.1", "policy_id": "pol_6538"}}, "risk": {"signal": "DENY_SIGNAL", "metadata": {"provider": "risk_provider_4", "version": "2.6", "risk_score": 0.644}}, "approval": {"signal": "DENY_SIGNAL", "metadata": {"provider": "approval_provider_5", "version": "2.3", "workflow_id": "wf_41276"}}, "registry": {"signal": "DENY_SIGNAL", "metadata": {"provider": "registry_provider_2", "version": "2.1", "registry_id": "reg_247"}}, "temporal": {"signal": "DENY_SIGNAL", "metadata": {"provider": "temporal_provider_3", "version": "1.2"}}}}, {"scenario_id": "arm-2-083", "arm": 2, "requester_id": "5fd25cae-629c-db81-b801-eaa9df9cbdd1", "action_type": "execute", "resource": "res_nzix9dgbebpr", "timestamp_utc": "2026-07-12T00:39:12.972046Z", "evidence_sources": {"identity": {"signal": "DENY_SIGNAL", "metadata": {"provider": "identity_provider_3", "version": "1.2"}}, "policy": {"signal": "DENY_SIGNAL", "metadata": {"provider": "policy_provider_2", "version": "3.8", "policy_id": "pol_6799"}}, "risk": {"signal": "DENY_SIGNAL", "metadata": {"provider": "risk_provider_4", "version": "1.0", "risk_score": 0.535}}, "approval": {"signal": "DENY_SIGNAL", "metadata": {"provider": "approval_provider_1", "version": "3.9", "workflow_id": "wf_44875"}}, "registry": {"signal": "DENY_SIGNAL", "metadata": {"provider": "registry_provider_3", "version": "2.5", "registry_id": "reg_290"}}, "temporal": {"signal": "DENY_SIGNAL", "metadata": {"provider": "temporal_provider_3", "version": "3.1"}}}}, {"scenario_id": "arm-2-084", "arm": 2, "requester_id": "10cd1dea-1091-ce69-e0e2-7bb3dd5dc919", "action_type": "approve", "resource": "item_vkdmy6yq5oyh", "timestamp_utc": "2026-06-19T05:06:12.972065Z", "evidence_sources": {"identity": {"signal": "DENY_SIGNAL", "metadata": {"provider": "identity_provider_2", "version": "2.2"}}, "policy": {"signal": "DENY_SIGNAL", "metadata": {"provider": "policy_provider_1", "version": "1.8", "policy_id": "pol_7609"}}, "risk": {"signal": "DENY_SIGNAL", "metadata": {"provider": "risk_provider_3", "version": "3.1", "risk_score": 0.362}}, "approval": {"signal": "DENY_SIGNAL", "metadata": {"provider": "approval_provider_1", "version": "3.3", "workflow_id": "wf_53701"}}, "registry": {"signal": "DENY_SIGNAL", "metadata": {"provider": "registry_provider_4", "version": "1.9", "registry_id": "reg_610"}}, "temporal": {"signal": "DENY_SIGNAL", "metadata": {"provider": "temporal_provider_3", "version": "3.1"}}}}, {"scenario_id": "arm-2-085", "arm": 2, "requester_id": "bcfb69df-8e1f-a52f-98db-4b9d255e9a5e", "action_type": "transfer", "resource": "obj_ljao67q4ml19", "timestamp_utc": "2026-06-19T20:58:12.972084Z", "evidence_sources": {"identity": {"signal": "DENY_SIGNAL", "metadata": {"provider": "identity_provider_4", "version": "3.0"}}, "policy": {"signal": "DENY_SIGNAL", "metadata": {"provider": "policy_provider_1", "version": "3.7", "policy_id": "pol_4936"}}, "risk": {"signal": "DENY_SIGNAL", "metadata": {"provider": "risk_provider_5", "version": "3.6", "risk_score": 0.877}}, "approval": {"signal": "DENY_SIGNAL", "metadata": {"provider": "approval_provider_2", "version": "3.0", "workflow_id": "wf_81572"}}, "registry": {"signal": "DENY_SIGNAL", "metadata": {"provider": "registry_provider_2", "version": "3.5", "registry_id": "reg_521"}}, "temporal": {"signal": "DENY_SIGNAL", "metadata": {"provider": "temporal_provider_4", "version": "1.6"}}}}, {"scenario_id": "arm-2-086", "arm": 2, "requester_id": "744f5f8c-c42c-e7e2-c3ff-bf39ad86ffed", "action_type": "approve", "resource": "asset_c3tg7an4ayfs", "timestamp_utc": "2026-07-01T05:54:12.972104Z", "evidence_sources": {"identity": {"signal": "DENY_SIGNAL", "metadata": {"provider": "identity_provider_4", "version": "2.2"}}, "policy": {"signal": "DENY_SIGNAL", "metadata": {"provider": "policy_provider_1", "version": "1.5", "policy_id": "pol_8972"}}, "risk": {"signal": "DENY_SIGNAL", "metadata": {"provider": "risk_provider_3", "version": "1.7", "risk_score": 0.947}}, "approval": {"signal": "DENY_SIGNAL", "metadata": {"provider": "approval_provider_4", "version": "1.1", "workflow_id": "wf_96210"}}, "registry": {"signal": "DENY_SIGNAL", "metadata": {"provider": "registry_provider_5", "version": "1.6", "registry_id": "reg_388"}}, "temporal": {"signal": "DENY_SIGNAL", "metadata": {"provider": "temporal_provider_4", "version": "2.5"}}}}, {"scenario_id": "arm-2-087", "arm": 2, "requester_id": "000cffab-f4ad-4256-fe23-8abe455db375", "action_type": "execute", "resource": "obj_7y4vyghaeyqs", "timestamp_utc": "2026-07-09T23:28:12.972124Z", "evidence_sources": {"identity": {"signal": "DENY_SIGNAL", "metadata": {"provider": "identity_provider_4", "version": "2.5"}}, "policy": {"signal": "DENY_SIGNAL", "metadata": {"provider": "policy_provider_3", "version": "2.4", "policy_id": "pol_8412"}}, "risk": {"signal": "DENY_SIGNAL", "metadata": {"provider": "risk_provider_4", "version": "2.6", "risk_score": 0.749}}, "approval": {"signal": "DENY_SIGNAL", "metadata": {"provider": "approval_provider_5", "version": "1.2", "workflow_id": "wf_92540"}}, "registry": {"signal": "DENY_SIGNAL", "metadata": {"provider": "registry_provider_5", "version": "1.5", "registry_id": "reg_902"}}, "temporal": {"signal": "DENY_SIGNAL", "metadata": {"provider": "temporal_provider_1", "version": "3.2"}}}}, {"scenario_id": "arm-2-088", "arm": 2, "requester_id": "aab2dd3b-dbbe-1fc1-76da-d7db26dafebf", "action_type": "transfer", "resource": "item_k7kmp3i593vh", "timestamp_utc": "2026-07-01T15:36:12.972143Z", "evidence_sources": {"identity": {"signal": "DENY_SIGNAL", "metadata": {"provider": "identity_provider_1", "version": "1.7"}}, "policy": {"signal": "DENY_SIGNAL", "metadata": {"provider": "policy_provider_4", "version": "2.8", "policy_id": "pol_4728"}}, "risk": {"signal": "DENY_SIGNAL", "metadata": {"provider": "risk_provider_3", "version": "2.6", "risk_score": 0.58}}, "approval": {"signal": "DENY_SIGNAL", "metadata": {"provider": "approval_provider_3", "version": "3.4", "workflow_id": "wf_86518"}}, "registry": {"signal": "DENY_SIGNAL", "metadata": {"provider": "registry_provider_2", "version": "3.5", "registry_id": "reg_103"}}, "temporal": {"signal": "DENY_SIGNAL", "metadata": {"provider": "temporal_provider_2", "version": "2.9"}}}}, {"scenario_id": "arm-2-089", "arm": 2, "requester_id": "8fe0e08b-bd4f-1dec-3e73-5ed87d9dced4", "action_type": "transfer", "resource": "obj_7dy8m7x0cy2s", "timestamp_utc": "2026-06-21T01:58:12.972181Z", "evidence_sources": {"identity": {"signal": "DENY_SIGNAL", "metadata": {"provider": "identity_provider_2", "version": "1.2"}}, "policy": {"signal": "DENY_SIGNAL", "metadata": {"provider": "policy_provider_5", "version": "2.7", "policy_id": "pol_1991"}}, "risk": {"signal": "DENY_SIGNAL", "metadata": {"provider": "risk_provider_2", "version": "1.5", "risk_score": 0.325}}, "approval": {"signal": "DENY_SIGNAL", "metadata": {"provider": "approval_provider_2", "version": "3.2", "workflow_id": "wf_35427"}}, "registry": {"signal": "DENY_SIGNAL", "metadata": {"provider": "registry_provider_2", "version": "1.5", "registry_id": "reg_441"}}, "temporal": {"signal": "DENY_SIGNAL", "metadata": {"provider": "temporal_provider_4", "version": "2.1"}}}}, {"scenario_id": "arm-2-090", "arm": 2, "requester_id": "e8f9e3be-6f04-e916-942d-bc82e18c94e6", "action_type": "revoke", "resource": "asset_pvtd4m64jhb5", "timestamp_utc": "2026-06-29T09:41:12.972202Z", "evidence_sources": {"identity": {"signal": "DENY_SIGNAL", "metadata": {"provider": "identity_provider_1", "version": "2.3"}}, "policy": {"signal": "DENY_SIGNAL", "metadata": {"provider": "policy_provider_4", "version": "2.0", "policy_id": "pol_4252"}}, "risk": {"signal": "DENY_SIGNAL", "metadata": {"provider": "risk_provider_5", "version": "1.6", "risk_score": 0.482}}, "approval": {"signal": "DENY_SIGNAL", "metadata": {"provider": "approval_provider_2", "version": "2.7", "workflow_id": "wf_68805"}}, "registry": {"signal": "DENY_SIGNAL", "metadata": {"provider": "registry_provider_2", "version": "3.2", "registry_id": "reg_570"}}, "temporal": {"signal": "DENY_SIGNAL", "metadata": {"provider": "temporal_provider_1", "version": "3.8"}}}}, {"scenario_id": "arm-2-091", "arm": 2, "requester_id": "2025afde-8f07-33fa-38ef-aadeba9afc8d", "action_type": "revoke", "resource": "asset_1t3fdalhgrr8", "timestamp_utc": "2026-06-19T03:22:12.972222Z", "evidence_sources": {"identity": {"signal": "DENY_SIGNAL", "metadata": {"provider": "identity_provider_2", "version": "2.6"}}, "policy": {"signal": "DENY_SIGNAL", "metadata": {"provider": "policy_provider_2", "version": "3.4", "policy_id": "pol_6247"}}, "risk": {"signal": "DENY_SIGNAL", "metadata": {"provider": "risk_provider_4", "version": "2.9", "risk_score": 0.098}}, "approval": {"signal": "DENY_SIGNAL", "metadata": {"provider": "approval_provider_2", "version": "2.6", "workflow_id": "wf_52641"}}, "registry": {"signal": "DENY_SIGNAL", "metadata": {"provider": "registry_provider_3", "version": "3.7", "registry_id": "reg_723"}}, "temporal": {"signal": "DENY_SIGNAL", "metadata": {"provider": "temporal_provider_3", "version": "2.0"}}}}, {"scenario_id": "arm-2-092", "arm": 2, "requester_id": "c25baaf5-f8d9-d5dd-dac0-149501ddfaa4", "action_type": "approve", "resource": "item_q9r54nvj7a8t", "timestamp_utc": "2026-07-06T21:43:12.972242Z", "evidence_sources": {"identity": {"signal": "DENY_SIGNAL", "metadata": {"provider": "identity_provider_4", "version": "2.6"}}, "policy": {"signal": "DENY_SIGNAL", "metadata": {"provider": "policy_provider_1", "version": "3.2", "policy_id": "pol_2557"}}, "risk": {"signal": "DENY_SIGNAL", "metadata": {"provider": "risk_provider_5", "version": "3.3", "risk_score": 0.459}}, "approval": {"signal": "DENY_SIGNAL", "metadata": {"provider": "approval_provider_2", "version": "2.6", "workflow_id": "wf_82544"}}, "registry": {"signal": "DENY_SIGNAL", "metadata": {"provider": "registry_provider_5", "version": "1.7", "registry_id": "reg_972"}}, "temporal": {"signal": "DENY_SIGNAL", "metadata": {"provider": "temporal_provider_5", "version": "2.9"}}}}, {"scenario_id": "arm-2-093", "arm": 2, "requester_id": "7d40a249-da3e-86ba-4caf-c48180acd58f", "action_type": "revoke", "resource": "res_q8tty76jbgzc", "timestamp_utc": "2026-06-21T06:36:12.972263Z", "evidence_sources": {"identity": {"signal": "DENY_SIGNAL", "metadata": {"provider": "identity_provider_4", "version": "1.0"}}, "policy": {"signal": "DENY_SIGNAL", "metadata": {"provider": "policy_provider_3", "version": "2.8", "policy_id": "pol_7188"}}, "risk": {"signal": "DENY_SIGNAL", "metadata": {"provider": "risk_provider_1", "version": "2.0", "risk_score": 0.547}}, "approval": {"signal": "DENY_SIGNAL", "metadata": {"provider": "approval_provider_1", "version": "1.4", "workflow_id": "wf_41867"}}, "registry": {"signal": "DENY_SIGNAL", "metadata": {"provider": "registry_provider_5", "version": "2.7", "registry_id": "reg_259"}}, "temporal": {"signal": "DENY_SIGNAL", "metadata": {"provider": "temporal_provider_5", "version": "1.2"}}}}, {"scenario_id": "arm-2-094", "arm": 2, "requester_id": "70af024a-479e-bcd3-5fb9-ac50cb8fd027", "action_type": "transfer", "resource": "res_twlmiuwkl5t3", "timestamp_utc": "2026-06-28T18:17:12.972282Z", "evidence_sources": {"identity": {"signal": "DENY_SIGNAL", "metadata": {"provider": "identity_provider_5", "version": "2.4"}}, "policy": {"signal": "DENY_SIGNAL", "metadata": {"provider": "policy_provider_1", "version": "1.9", "policy_id": "pol_1657"}}, "risk": {"signal": "DENY_SIGNAL", "metadata": {"provider": "risk_provider_1", "version": "1.1", "risk_score": 0.131}}, "approval": {"signal": "DENY_SIGNAL", "metadata": {"provider": "approval_provider_2", "version": "3.7", "workflow_id": "wf_81159"}}, "registry": {"signal": "DENY_SIGNAL", "metadata": {"provider": "registry_provider_4", "version": "3.8", "registry_id": "reg_610"}}, "temporal": {"signal": "DENY_SIGNAL", "metadata": {"provider": "temporal_provider_5", "version": "3.9"}}}}, {"scenario_id": "arm-2-095", "arm": 2, "requester_id": "71d0bc0d-93a4-eef9-ddd4-20fc596cdae1", "action_type": "revoke", "resource": "res_kwapehzqilef", "timestamp_utc": "2026-07-12T01:00:12.972302Z", "evidence_sources": {"identity": {"signal": "DENY_SIGNAL", "metadata": {"provider": "identity_provider_1", "version": "2.6"}}, "policy": {"signal": "DENY_SIGNAL", "metadata": {"provider": "policy_provider_4", "version": "1.0", "policy_id": "pol_9424"}}, "risk": {"signal": "DENY_SIGNAL", "metadata": {"provider": "risk_provider_2", "version": "1.6", "risk_score": 0.7}}, "approval": {"signal": "DENY_SIGNAL", "metadata": {"provider": "approval_provider_5", "version": "3.5", "workflow_id": "wf_13425"}}, "registry": {"signal": "DENY_SIGNAL", "metadata": {"provider": "registry_provider_2", "version": "2.1", "registry_id": "reg_861"}}, "temporal": {"signal": "DENY_SIGNAL", "metadata": {"provider": "temporal_provider_5", "version": "2.6"}}}}, {"scenario_id": "arm-2-096", "arm": 2, "requester_id": "baf92ea8-ecc9-5aa1-02eb-e376badba8de", "action_type": "approve", "resource": "item_p1tiwk2q0hsv", "timestamp_utc": "2026-06-25T22:18:12.972322Z", "evidence_sources": {"identity": {"signal": "DENY_SIGNAL", "metadata": {"provider": "identity_provider_2", "version": "3.3"}}, "policy": {"signal": "DENY_SIGNAL", "metadata": {"provider": "policy_provider_4", "version": "1.2", "policy_id": "pol_5007"}}, "risk": {"signal": "DENY_SIGNAL", "metadata": {"provider": "risk_provider_1", "version": "2.6", "risk_score": 0.329}}, "approval": {"signal": "DENY_SIGNAL", "metadata": {"provider": "approval_provider_2", "version": "3.4", "workflow_id": "wf_30825"}}, "registry": {"signal": "DENY_SIGNAL", "metadata": {"provider": "registry_provider_4", "version": "3.5", "registry_id": "reg_139"}}, "temporal": {"signal": "DENY_SIGNAL", "metadata": {"provider": "temporal_provider_3", "version": "3.2"}}}}, {"scenario_id": "arm-2-097", "arm": 2, "requester_id": "dd0a9c94-bc87-fcc5-ec01-e1dc48dbd053", "action_type": "delegate", "resource": "res_vsztf7547gic", "timestamp_utc": "2026-06-22T05:12:12.972341Z", "evidence_sources": {"identity": {"signal": "DENY_SIGNAL", "metadata": {"provider": "identity_provider_4", "version": "3.0"}}, "policy": {"signal": "DENY_SIGNAL", "metadata": {"provider": "policy_provider_4", "version": "3.9", "policy_id": "pol_7096"}}, "risk": {"signal": "DENY_SIGNAL", "metadata": {"provider": "risk_provider_4", "version": "2.6", "risk_score": 0.931}}, "approval": {"signal": "DENY_SIGNAL", "metadata": {"provider": "approval_provider_5", "version": "1.0", "workflow_id": "wf_25697"}}, "registry": {"signal": "DENY_SIGNAL", "metadata": {"provider": "registry_provider_4", "version": "3.4", "registry_id": "reg_794"}}, "temporal": {"signal": "DENY_SIGNAL", "metadata": {"provider": "temporal_provider_4", "version": "3.9"}}}}, {"scenario_id": "arm-2-098", "arm": 2, "requester_id": "482bea5b-0b7d-b67d-ca7b-28d76df2a73d", "action_type": "delegate", "resource": "obj_l0s1gd1r4nla", "timestamp_utc": "2026-06-21T08:04:12.972360Z", "evidence_sources": {"identity": {"signal": "DENY_SIGNAL", "metadata": {"provider": "identity_provider_4", "version": "2.2"}}, "policy": {"signal": "DENY_SIGNAL", "metadata": {"provider": "policy_provider_4", "version": "3.0", "policy_id": "pol_3752"}}, "risk": {"signal": "DENY_SIGNAL", "metadata": {"provider": "risk_provider_3", "version": "3.3", "risk_score": 0.622}}, "approval": {"signal": "DENY_SIGNAL", "metadata": {"provider": "approval_provider_3", "version": "1.1", "workflow_id": "wf_40157"}}, "registry": {"signal": "DENY_SIGNAL", "metadata": {"provider": "registry_provider_4", "version": "1.4", "registry_id": "reg_655"}}, "temporal": {"signal": "DENY_SIGNAL", "metadata": {"provider": "temporal_provider_5", "version": "1.3"}}}}, {"scenario_id": "arm-2-099", "arm": 2, "requester_id": "fdfef668-aacd-b5aa-98fc-3b4fc4140fac", "action_type": "approve", "resource": "obj_r5wkdd8gbsi0", "timestamp_utc": "2026-06-17T03:35:12.972379Z", "evidence_sources": {"identity": {"signal": "DENY_SIGNAL", "metadata": {"provider": "identity_provider_2", "version": "3.5"}}, "policy": {"signal": "DENY_SIGNAL", "metadata": {"provider": "policy_provider_4", "version": "1.3", "policy_id": "pol_5322"}}, "risk": {"signal": "DENY_SIGNAL", "metadata": {"provider": "risk_provider_4", "version": "1.4", "risk_score": 0.682}}, "approval": {"signal": "DENY_SIGNAL", "metadata": {"provider": "approval_provider_3", "version": "1.7", "workflow_id": "wf_54324"}}, "registry": {"signal": "DENY_SIGNAL", "metadata": {"provider": "registry_provider_5", "version": "1.8", "registry_id": "reg_357"}}, "temporal": {"signal": "DENY_SIGNAL", "metadata": {"provider": "temporal_provider_4", "version": "1.0"}}}}]